{
  "x_breaking": [],
  "breaking": [
    {
      "title": "Starknet TVL reclaims $300m for first time since 2024 as on-chain activity recovers",
      "link": "https://ambcrypto.com/starknet-tvl-reclaims-300m-for-first-time-since-2024-as-on-chain-activity-recovers/",
      "published_at": "2026-01-14T16:21:51+00:00",
      "source": "ambcrypto.com",
      "score": 2,
      "ntitle": "starknet tvl reclaims 300m first time since 2024 as chain activity recovers"
    },
    {
      "title": "Monero's XMR Token Surpasses $700",
      "link": "https://www.bankless.com/read/news/monero-hits-8-year-high-over-700",
      "published_at": "2026-01-14T15:33:15+00:00",
      "source": "bankless.com",
      "score": 0,
      "ntitle": "monero s xmr token surpasses 700"
    },
    {
      "title": "Here’s Why The Bitcoin, Ethereum, And Dogecoin Prices Are Surging Today",
      "link": "https://bitcoinist.com/bitcoin-ethereum-dogecoin-prices-2/",
      "published_at": "2026-01-14T15:30:16+00:00",
      "source": "bitcoinist.com",
      "score": 1,
      "ntitle": "here s why bitcoin ethereum dogecoin prices surging today"
    },
    {
      "title": "Celestia Unveils Vision 2.0, Targets 1Tbps Blockspace for Global Markets",
      "link": "https://Blockchain.News/news/celestia-vision-2-targets-1tbps-blockspace-global-markets",
      "published_at": "2026-01-14T16:13:47+00:00",
      "source": "blockchain.news",
      "score": 5,
      "ntitle": "celestia unveils vision 2 0 targets 1tbps blockspace global markets"
    },
    {
      "title": "Top AI Crypto Coins 2026: New Ethereum Wallets Record a Massive Uptick, DeepSnitch AI Enters the Final Stretch of Presale With $1.2M As Traders Await 100x Gains",
      "link": "https://blockonomi.com/top-ai-crypto-coins-2026-new-ethereum-wallets-record-a-massive-uptick-deepsnitch-ai-enters-the-final-stretch-of-presale-with-1-2m-as-traders-await-100x-gains/",
      "published_at": "2026-01-14T16:15:17+00:00",
      "source": "blockonomi.com",
      "score": 2,
      "ntitle": "top ai crypto coins 2026 new ethereum wallets record massive uptick deepsnitch ai enters final stretch presale 1 2m as traders await 100x gains"
    },
    {
      "title": "Netflix likely to adjust Warner Bros. Discovery offer to make it all-cash",
      "link": "https://www.cnbc.com/2026/01/14/netflix-warner-bros-discovery-deal-all-cash.html",
      "published_at": "2026-01-14T16:22:32+00:00",
      "source": "cnbc.com",
      "score": 3,
      "ntitle": "netflix likely adjust warner bros discovery offer make it all cash"
    },
    {
      "title": "Bitcoin rallies past $97,000 as investors seek haven assets",
      "link": "https://www.coindesk.com/markets/2026/01/14/bitcoin-rallies-past-usd97-000-as-investors-seek-haven-assets",
      "published_at": "2026-01-14T16:14:46+00:00",
      "source": "coindesk.com",
      "score": 1,
      "ntitle": "bitcoin rallies past 97 000 as investors seek haven assets"
    },
    {
      "title": "MSTR Stock Rises as Bitcoin Hits New 2026 High; Expert Predicts $455 Target",
      "link": "https://coingape.com/news/stocks/mstr-stock-rises-as-bitcoin-hits-97k-expert-predicts-455-target/",
      "published_at": "2026-01-14T16:21:06+00:00",
      "source": "coingape.com",
      "score": 1,
      "ntitle": "mstr stock rises as bitcoin hits new 2026 high expert predicts 455 target"
    },
    {
      "title": "Arthur Hayes eyes Ethena price surge to $1 as major Korean exchanges list USDe",
      "link": "https://coinjournal.net/news/arthur-hayes-eyes-ethena-price-surge-to-1-as-major-korean-exchanges-list-usde/",
      "published_at": "2026-01-14T15:29:07+00:00",
      "source": "coinjournal.net",
      "score": 3,
      "ntitle": "arthur hayes eyes ethena price surge 1 as major korean exchanges list usde"
    },
    {
      "title": "Dash price soars 125% amid privacy coin boom: Is the rally overheating?",
      "link": "https://cointelegraph.com/news/dash-price-soars-privacy-coin-boom-is-rally-overheating?utm_source=rss_feed&utm_medium=rss&utm_campaign=rss_partner_inbound",
      "published_at": "2026-01-14T16:22:25+00:00",
      "source": "cointelegraph.com",
      "score": 1,
      "ntitle": "dash price soars 125 amid privacy coin boom rally overheating"
    },
    {
      "title": "Monero price prediction: Will XMR break records after $722 ATH?",
      "link": "https://crypto.news/monero-price-prediction-will-xmr-break-new-records/",
      "published_at": "2026-01-14T16:07:47+00:00",
      "source": "crypto.news",
      "score": 1,
      "ntitle": "monero price prediction will xmr break records after 722 ath"
    },
    {
      "title": "Sui mainnet faces a network stall, core team working on a fix",
      "link": "https://cryptobriefing.com/sui-mainnet-network-stall-issue-january-2026/",
      "published_at": "2026-01-14T16:19:48+00:00",
      "source": "cryptobriefing.com",
      "score": 3,
      "ntitle": "sui mainnet faces network stall core team working fix"
    },
    {
      "title": "This ICP Metric Soars to a 2-Month High After 19% Surge: Pullback on the Way?",
      "link": "https://cryptopotato.com/this-icp-metric-soars-to-a-2-month-high-after-19-surge-pullback-on-the-way/",
      "published_at": "2026-01-14T15:57:20+00:00",
      "source": "cryptopotato.com",
      "score": 1,
      "ntitle": "this icp metric soars 2 month high after 19 surge pullback way"
    },
    {
      "title": "Data reveals the new “sweet spot” for crypto in your portfolio as financial advisors flip aggressive on Bitcoin",
      "link": "https://cryptoslate.com/financial-advisors-flip-aggressive-on-bitcoin-as-data-reveals-the-new-sweet-spot-for-crypto-holdings/",
      "published_at": "2026-01-14T15:45:01+00:00",
      "source": "cryptoslate.com",
      "score": 2,
      "ntitle": "data reveals new sweet spot crypto your portfolio as financial advisors flip aggressive bitcoin"
    },
    {
      "title": "Solana Altcoin Jumps As Crypto Giant Coinbase Announces Trading Support",
      "link": "https://dailyhodl.com/2026/01/14/solana-altcoin-jumps-as-crypto-giant-coinbase-announces-trading-support/",
      "published_at": "2026-01-14T15:40:56+00:00",
      "source": "dailyhodl.com",
      "score": 1,
      "ntitle": "solana altcoin jumps as crypto giant coinbase announces trading support"
    },
    {
      "title": "LINK Hits Monthly High as Bitwise Launches Chainlink ETF on NYSE",
      "link": "https://decrypt.co/354569/link-monthly-high-bitwise-chainlink-etf-nyse",
      "published_at": "2026-01-14T16:11:22+00:00",
      "source": "decrypt.co",
      "score": 12,
      "ntitle": "link hits monthly high as bitwise launches chainlink etf nyse"
    },
    {
      "title": "Korean Volume Surges, Charts Sizzle: XRP Prepares for Its Next Power Move",
      "link": "https://news.bitcoin.com/korean-volume-surges-charts-sizzle-xrp-prepares-for-its-next-power-move/",
      "published_at": "2026-01-14T16:15:58+00:00",
      "source": "news.bitcoin.com",
      "score": 6,
      "ntitle": "korean volume surges charts sizzle xrp prepares its next power move"
    },
    {
      "title": "Bitcoin At $100K Could Spark A Fresh Wave Of Retail FOMO, Analysts Warn",
      "link": "https://www.newsbtc.com/news/bitcoin/bitcoin-at-100k-could-spark-a-fresh-wave-of-retail-fomo-analysts-warn/",
      "published_at": "2026-01-14T15:30:25+00:00",
      "source": "newsbtc.com",
      "score": 3,
      "ntitle": "bitcoin at 100k could spark fresh wave retail fomo analysts warn"
    },
    {
      "title": "Bitcoin Nears $97K as Broad Crypto Rally Extends for Second Day",
      "link": "https://thedefiant.io/news/markets/bitcoin-nears-usd97k-in-broad-crypto-rally-jan-14-2026",
      "published_at": "2026-01-14T15:53:52+00:00",
      "source": "thedefiant.io",
      "score": 5,
      "ntitle": "bitcoin nears 97k as broad crypto rally extends second day"
    },
    {
      "title": "Bitcoin (BTC) Price Analysis for January 14",
      "link": "https://u.today/bitcoin-btc-price-analysis-for-january-14-0",
      "published_at": "2026-01-14T16:05:00+00:00",
      "source": "u.today",
      "score": 1,
      "ntitle": "bitcoin btc price analysis january 14"
    },
    {
      "title": "Why is XRP’s price up today? ETF inflows, cooling CPI lifts & more…",
      "link": "https://ambcrypto.com/why-is-xrps-price-up-today-etf-inflows-cooling-cpi-lifts-more/",
      "published_at": "2026-01-14T16:00:29+00:00",
      "source": "ambcrypto.com",
      "score": 8,
      "ntitle": "why xrp s price up today etf inflows cooling cpi lifts more"
    },
    {
      "title": "Meta's Manus AI Reveals Sandbox Architecture Behind Autonomous Agent Tasks",
      "link": "https://Blockchain.News/news/meta-manus-ai-sandbox-architecture-autonomous-agents",
      "published_at": "2026-01-14T16:05:02+00:00",
      "source": "blockchain.news",
      "score": 1,
      "ntitle": "meta s manus ai reveals sandbox architecture behind autonomous agent tasks"
    },
    {
      "title": "Quant and Dentsu Soken Partner to Advance Japan’s Tokenized Deposit Infrastructure",
      "link": "https://blockonomi.com/quant-and-dentsu-soken-partner-to-advance-japans-tokenized-deposit-infrastructure/",
      "published_at": "2026-01-14T16:04:55+00:00",
      "source": "blockonomi.com",
      "score": 14,
      "ntitle": "quant dentsu soken partner advance japan s tokenized deposit infrastructure"
    },
    {
      "title": "Big banks want to freeze innovation. History says that’s a mistake",
      "link": "https://www.coindesk.com/opinion/2026/01/14/big-banks-want-to-freeze-innovation-history-says-that-s-a-mistake",
      "published_at": "2026-01-14T16:11:59+00:00",
      "source": "coindesk.com",
      "score": 3,
      "ntitle": "big banks want freeze innovation history says that s mistake"
    },
    {
      "title": "Crypto ETF News: Bitwise Launches Chainlink ETF as Institutional Inflows Return",
      "link": "https://coingape.com/crypto-etf-news-bitwise-launches-chainlink-etf-inflows-return/",
      "published_at": "2026-01-14T16:07:51+00:00",
      "source": "coingape.com",
      "score": 14,
      "ntitle": "crypto etf news bitwise launches chainlink etf as institutional inflows return"
    },
    {
      "title": "Why US community banks say the GENIUS Act has a stablecoin loophole",
      "link": "https://cointelegraph.com/news/why-us-community-banks-say-the-genius-act-has-a-stablecoin-loophole?utm_source=rss_feed&utm_medium=rss&utm_campaign=rss_partner_inbound",
      "published_at": "2026-01-14T16:08:35+00:00",
      "source": "cointelegraph.com",
      "score": 3,
      "ntitle": "why us community banks say genius act has stablecoin loophole"
    },
    {
      "title": "Solana price eyes a 40% surge as active addresses hits 6-month high",
      "link": "https://crypto.news/solana-price-eyes-40-active-addresses-6-month-high/",
      "published_at": "2026-01-14T16:00:00+00:00",
      "source": "crypto.news",
      "score": 1,
      "ntitle": "solana price eyes 40 surge as active addresses hits 6 month high"
    },
    {
      "title": "Algorand Foundation returns to the US, appoints new board for strategic blockchain initiatives",
      "link": "https://cryptobriefing.com/algorand-foundation-us-blockchain-board/",
      "published_at": "2026-01-14T15:53:53+00:00",
      "source": "cryptobriefing.com",
      "score": 2,
      "ntitle": "algorand foundation returns us appoints new board strategic blockchain initiatives"
    },
    {
      "title": "World Liberty Financial Stablecoin USD1 Lands on Prediction Market Myriad",
      "link": "https://decrypt.co/353044/world-liberty-financial-stablecoin-usd1-lands-on-prediction-market-myriad",
      "published_at": "2026-01-14T16:06:14+00:00",
      "source": "decrypt.co",
      "score": 5,
      "ntitle": "world liberty financial stablecoin usd1 lands prediction market myriad"
    },
    {
      "title": "Mantra Cuts Staff Less Than a Year After OM Crashed 90%",
      "link": "https://thedefiant.io/news/blockchains/mantra-cuts-staff-after-token-crash",
      "published_at": "2026-01-14T15:31:35+00:00",
      "source": "thedefiant.io",
      "score": 1,
      "ntitle": "mantra cuts staff less than year after om crashed 90"
    }
  ],
  "day": [
    {
      "title": "Digitap ($TAP) vs $3,100 ETH: Why this Banking Crypto Presale is the 2026 10x Winner",
      "link": "https://ambcrypto.com/digitap-tap-vs-3100-eth-why-this-banking-crypto-presale-is-the-2026-10x-winner/",
      "published_at": "2026-01-14T15:00:52+00:00",
      "source": "ambcrypto.com",
      "score": 4,
      "ntitle": "digitap tap vs 3 100 eth why this banking crypto presale 2026 10x winner"
    },
    {
      "title": "5 Highlights from the U.S. Senate's Much-Hyped Crypto Market Structure Draft Bill",
      "link": "https://www.bankless.com/read/5-highlights-from-the-senates-much-hyped-crypto-market-structure-draft-bill",
      "published_at": "2026-01-13T22:01:35+00:00",
      "source": "bankless.com",
      "score": 2,
      "ntitle": "5 highlights u s senate s much hyped crypto market structure draft bill"
    },
    {
      "title": "XRP Slides Toward $2 as Oversold Signals Hint at Relief Rally",
      "link": "https://beincrypto.com/xrp-holders-can-relax-as-price-rises/",
      "published_at": "2026-01-14T14:00:00+00:00",
      "source": "beincrypto.com",
      "score": 6,
      "ntitle": "xrp slides toward 2 as oversold signals hint at relief rally"
    },
    {
      "title": "Crypto’s Big Regulatory Overhaul May Crawl Through Years Of Policy Creation: Exec",
      "link": "https://bitcoinist.com/cryptos-big-regulatory-overhaul-may-crawl-through-years-of-rulemaking-exec/",
      "published_at": "2026-01-14T14:00:15+00:00",
      "source": "bitcoinist.com",
      "score": 2,
      "ntitle": "crypto s big regulatory overhaul may crawl through years policy creation exec"
    },
    {
      "title": "Rhode Island Reintroduces Bitcoin Tax Exemption Bill for Second Straight Year",
      "link": "https://bitcoinmagazine.com/news/rhode-island-reintroduces-bitcoin-tax-bill",
      "published_at": "2026-01-14T13:15:05+00:00",
      "source": "bitcoinmagazine.com",
      "score": 1,
      "ntitle": "rhode island reintroduces bitcoin tax exemption bill second straight year"
    },
    {
      "title": "AAVE Price Prediction: Targets $190-195 by February 2026 Amid Technical Recovery",
      "link": "https://Blockchain.News/news/20260114-price-prediction-aave-targets-190-195-by-february-2026",
      "published_at": "2026-01-14T15:20:28+00:00",
      "source": "blockchain.news",
      "score": 2,
      "ntitle": "aave price prediction targets 190 195 february 2026 amid technical recovery"
    },
    {
      "title": "As Stablecoins Disrupt Global Payments, Digitap’s ($TAP) Visa Card Bridges the Retail Gap",
      "link": "https://blockonomi.com/as-stablecoins-disrupt-global-payments-digitaps-tap-visa-card-bridges-the-retail-gap/",
      "published_at": "2026-01-14T15:00:30+00:00",
      "source": "blockonomi.com",
      "score": 2,
      "ntitle": "as stablecoins disrupt global payments digitap s tap visa card bridges retail gap"
    },
    {
      "title": "2025年、なりすまし手口とAI活用の急増で暗号資産詐欺・不正被害額が過去最高の約170億ドルに",
      "link": "https://www.chainalysis.com/blog/crypto-scams-2026-japanese/",
      "published_at": "2026-01-13T22:33:26+00:00",
      "source": "chainalysis.com",
      "score": 1,
      "ntitle": "2025 ai 170"
    },
    {
      "title": "Existing home sales end 2025 with a strong beat, as prices ease further",
      "link": "https://www.cnbc.com/2026/01/14/existing-home-sales-end-2025-stronger-than-expected.html",
      "published_at": "2026-01-14T15:13:16+00:00",
      "source": "cnbc.com",
      "score": 1,
      "ntitle": "existing home sales end 2025 strong beat as prices ease further"
    },
    {
      "title": "Bybit Pay links with digital wallets Yape, Plin to offer crypto payments in Peru",
      "link": "https://www.coindesk.com/business/2026/01/14/bybit-pay-links-with-digital-wallets-yape-plin-to-offer-crypto-payments-in-peru",
      "published_at": "2026-01-14T15:15:19+00:00",
      "source": "coindesk.com",
      "score": 4,
      "ntitle": "bybit pay links digital wallets yape plin offer crypto payments peru"
    },
    {
      "title": "Senators Make Amendments To CLARITY Act On Yield and DeFi Ahead Of Crypto Bill’s Markup",
      "link": "https://coingape.com/senators-file-clarity-act-amendments-on-yield-and-defi/",
      "published_at": "2026-01-14T14:47:31+00:00",
      "source": "coingape.com",
      "score": 8,
      "ntitle": "senators make amendments clarity act yield defi ahead crypto bill s markup"
    },
    {
      "title": "MANTRA announces team layoffs amid company restructuring",
      "link": "https://coinjournal.net/news/mantra-announces-team-layoffs-amid-company-restructuring/",
      "published_at": "2026-01-14T13:51:46+00:00",
      "source": "coinjournal.net",
      "score": 7,
      "ntitle": "mantra announces team layoffs amid company restructuring"
    },
    {
      "title": "Bitnomial opens first US-regulated futures market for Aptos",
      "link": "https://cointelegraph.com/news/bitnomial-opens-us-regulated-futures-market-for-aptos?utm_source=rss_feed&utm_medium=rss&utm_campaign=rss_partner_inbound",
      "published_at": "2026-01-14T15:07:23+00:00",
      "source": "cointelegraph.com",
      "score": 3,
      "ntitle": "bitnomial opens first us regulated futures market aptos"
    },
    {
      "title": "Over 20,000 investors bet big on this ‘next-gen XRP’ after missing out early on Ethereum and XRP",
      "link": "https://crypto.news/over-20000-investors-bet-big-on-this-next-gen-xrp-after-missing-out-early-on-ethereum-and-xrp/",
      "published_at": "2026-01-14T15:00:00+00:00",
      "source": "crypto.news",
      "score": 7,
      "ntitle": "over 20 000 investors bet big this next gen xrp after missing out early ethereum xrp"
    },
    {
      "title": "Rhode Island proposes bill to eliminate taxes on small Bitcoin payments",
      "link": "https://cryptobriefing.com/rhode-island-bitcoin-tax-exemption-small-transactions/",
      "published_at": "2026-01-14T14:27:57+00:00",
      "source": "cryptobriefing.com",
      "score": 1,
      "ntitle": "rhode island proposes bill eliminate taxes small bitcoin payments"
    },
    {
      "title": "Bitcoin Derivatives Enter Risk-On Mode as Futures Traders Go Aggressive",
      "link": "https://cryptopotato.com/bitcoin-derivatives-enter-risk-on-mode-as-futures-traders-go-aggressive/",
      "published_at": "2026-01-14T14:45:24+00:00",
      "source": "cryptopotato.com",
      "score": 1,
      "ntitle": "bitcoin derivatives enter risk mode as futures traders go aggressive"
    },
    {
      "title": "Bitcoin ignored Trump’s latest 25% tariff threat, but the $19B liquidation ghost from October is quietly resetting in the shadows",
      "link": "https://cryptoslate.com/bitcoin-ignored-trumps-new-25-tariff-threat-this-time-but-the-19b-liquidation-ghost-from-october-is-quietly-resetting-in-the-shadows/",
      "published_at": "2026-01-14T13:35:41+00:00",
      "source": "cryptoslate.com",
      "score": 3,
      "ntitle": "bitcoin ignored trump s latest 25 tariff threat but 19b liquidation ghost october quietly resetting shadows"
    },
    {
      "title": "Polygon Labs Spending $250,000,000 To Acquire Coinme and Sequence, Expand Into US Stablecoin Market",
      "link": "https://dailyhodl.com/2026/01/14/polygon-labs-spending-250000000-to-acquire-coinme-and-sequence-expand-into-us-stablecoin-market/",
      "published_at": "2026-01-14T10:15:29+00:00",
      "source": "dailyhodl.com",
      "score": 4,
      "ntitle": "polygon labs spending 250 000 000 acquire coinme sequence expand into us stablecoin market"
    },
    {
      "title": "Morning Minute: Financial Advisors Are More Bullish on Crypto Than Ever",
      "link": "https://decrypt.co/354555/morning-minute-financial-advisors-are-more-bullish-crypto-than-ever",
      "published_at": "2026-01-14T13:46:02+00:00",
      "source": "decrypt.co",
      "score": 1,
      "ntitle": "morning minute financial advisors more bullish crypto than ever"
    },
    {
      "title": "Federal Reserve Board announces approval of application by Fifth Third Bancorp",
      "link": "https://www.federalreserve.gov/newsevents/pressreleases/orders20260113a.htm",
      "published_at": "2026-01-13T22:30:00+00:00",
      "source": "federalreserve.gov",
      "score": 3,
      "ntitle": "federal reserve board announces approval application fifth third bancorp"
    },
    {
      "title": "The Altcoin Vector #37",
      "link": "https://insights.glassnode.com/the-altcoin-vector-37/",
      "published_at": "2026-01-14T08:25:32+00:00",
      "source": "insights.glassnode.com",
      "score": 0,
      "ntitle": "altcoin vector 37"
    },
    {
      "title": "Bitcoin price today: jumps above $96k after Strategy buy, but weakness persists",
      "link": "https://www.investing.com/news/cryptocurrency-news/bitcoin-tops-95k-after-strategy-buy-steady-cpi-4445913",
      "published_at": "2026-01-14T14:58:17+00:00",
      "source": "investing.com",
      "score": 1,
      "ntitle": "bitcoin price today jumps above 96k after strategy buy but weakness persists"
    },
    {
      "title": "Silver Nears $100 on Global Shortages While Geopolitics Lift Gold Higher",
      "link": "https://news.bitcoin.com/silver-nears-100-on-global-shortages-while-geopolitics-lift-gold-higher/",
      "published_at": "2026-01-14T15:11:21+00:00",
      "source": "news.bitcoin.com",
      "score": 1,
      "ntitle": "silver nears 100 global shortages while geopolitics lift gold higher"
    },
    {
      "title": "Analyst Outlines The Bulllish And Bearish Scenarios For Bitcoin – Here’s What To Know",
      "link": "https://www.newsbtc.com/news/bitcoin/bitcoin-bulllish-bearish-scenarios/",
      "published_at": "2026-01-14T14:00:20+00:00",
      "source": "newsbtc.com",
      "score": 4,
      "ntitle": "analyst outlines bulllish bearish scenarios bitcoin here s what know"
    },
    {
      "title": "Why crypto should have listened to Dilbert",
      "link": "https://protos.com/why-crypto-should-have-listened-to-dilbert/",
      "published_at": "2026-01-14T12:24:37+00:00",
      "source": "protos.com",
      "score": 1,
      "ntitle": "why crypto should have listened dilbert"
    },
    {
      "title": "Bitcoin Climbs Back Over $95K as Traders Digest New Inflation Data",
      "link": "https://thedefiant.io/news/markets/bitcoin-climbs-back-over-usd95k-as-traders-digest-new-inflation-data",
      "published_at": "2026-01-13T23:05:04+00:00",
      "source": "thedefiant.io",
      "score": 1,
      "ntitle": "bitcoin climbs back over 95k as traders digest new inflation data"
    },
    {
      "title": "$849,980,000 in 24 Hours: Cardano 13% Open Interest Surge Stuns Bears",
      "link": "https://u.today/849980000-in-24-hours-cardano-13-open-interest-surge-stuns-bears",
      "published_at": "2026-01-14T15:23:00+00:00",
      "source": "u.today",
      "score": 1,
      "ntitle": "849 980 000 24 hours cardano 13 open interest surge stuns bears"
    },
    {
      "title": "Bitcoin Breaks Out as Shorts Burn and ETF Flows Surge",
      "link": "https://unchainedcrypto.com/bitcoin-breaks-out-as-shorts-burn-and-etf-flows-surge/",
      "published_at": "2026-01-14T12:10:45+00:00",
      "source": "unchainedcrypto.com",
      "score": 3,
      "ntitle": "bitcoin breaks out as shorts burn etf flows surge"
    },
    {
      "title": "Why is Story’s [IP] price up 36% today despite weak network revenue?",
      "link": "https://ambcrypto.com/why-is-storys-ip-price-up-36-today-despite-weak-network-revenue/",
      "published_at": "2026-01-14T15:00:15+00:00",
      "source": "ambcrypto.com",
      "score": 1,
      "ntitle": "why story s ip price up 36 today despite weak network revenue"
    },
    {
      "title": "What TokenWorks Is Building Next",
      "link": "https://www.bankless.com/read/tokenworks-building-next",
      "published_at": "2026-01-13T21:39:21+00:00",
      "source": "bankless.com",
      "score": 0,
      "ntitle": "what tokenworks building next"
    }
  ],
  "week": [
    {
      "title": "Success Story: Sterling Brasher’s Learning Journey with 101 Blockchains",
      "link": "https://101blockchains.com/sterling-brasher-success-story/",
      "published_at": "2026-01-12T10:16:21+00:00",
      "source": "101blockchains.com",
      "score": 3,
      "ntitle": "success story sterling brasher s learning journey 101 blockchains"
    },
    {
      "title": "Crypto Custodian BitGo Announces IPO Pricing",
      "link": "https://www.bankless.com/read/news/crypto-custodian-bitgo-announces-ipo-pricing",
      "published_at": "2026-01-12T19:15:22+00:00",
      "source": "bankless.com",
      "score": 1,
      "ntitle": "crypto custodian bitgo announces ipo pricing"
    },
    {
      "title": "Samourai Letter #2: Notes From The Inside",
      "link": "https://bitcoinmagazine.com/culture/samourai-letter-2-notes-from-the-inside",
      "published_at": "2026-01-13T15:59:38+00:00",
      "source": "bitcoinmagazine.com",
      "score": 1,
      "ntitle": "samourai letter 2 notes inside"
    },
    {
      "title": "Celestia Unveils Fibre Protocol With 1Tb/s Throughput Goal",
      "link": "https://Blockchain.News/news/celestia-fibre-protocol-1tb-throughput",
      "published_at": "2026-01-13T15:55:05+00:00",
      "source": "blockchain.news",
      "score": 1,
      "ntitle": "celestia unveils fibre protocol 1tb s throughput goal"
    },
    {
      "title": "H100 Group Signs LOI To Acquire Swiss Bitcoin Treasury Firm Future Holdings",
      "link": "https://btctimes.com/h100-group-signs-loi-to-acquire-swiss-bitcoin-treasury-firm-future-holdings/",
      "published_at": "2026-01-12T17:25:38+00:00",
      "source": "btctimes.com",
      "score": 3,
      "ntitle": "h100 group signs loi acquire swiss bitcoin treasury firm future holdings"
    },
    {
      "title": "Chainalysis and BVNK Extend Partnership to Power Compliance in Self-Hosted Digital Asset Payments",
      "link": "https://www.chainalysis.com/blog/bvnk-partnership-powering-compliance-self-hosted-digital-asset-payments/",
      "published_at": "2026-01-13T14:25:23+00:00",
      "source": "chainalysis.com",
      "score": 6,
      "ntitle": "chainalysis bvnk extend partnership power compliance self hosted digital asset payments"
    },
    {
      "title": "IUX Official Website Review – What You Must Know",
      "link": "https://coincodecap.com/iux-review?utm_source=rss&utm_medium=rss&utm_campaign=iux-review",
      "published_at": "2026-01-13T15:39:30+00:00",
      "source": "coincodecap.com",
      "score": 1,
      "ntitle": "iux official website review what you must know"
    },
    {
      "title": "Uniswap Flips the Fee Switch: From Governance Token to Value Accrual",
      "link": "https://coinmetrics.io/state-of-the-network/uniswap-flips-the-fee-switch-from-governance-token-to-value-accrual/",
      "published_at": "2026-01-13T14:08:38+00:00",
      "source": "coinmetrics.io",
      "score": 3,
      "ntitle": "uniswap flips fee switch governance token value accrual"
    },
    {
      "title": "Bitcoin price trades in bear flag range, directional risk builds",
      "link": "https://crypto.news/bitcoin-price-trades-in-bear-flag-range-directional-risk-builds/",
      "published_at": "2026-01-13T16:00:35+00:00",
      "source": "crypto.news",
      "score": 1,
      "ntitle": "bitcoin price trades bear flag range directional risk builds"
    },
    {
      "title": "CoinGecko eyes potential sale valued at $500M",
      "link": "https://cryptobriefing.com/coingecko-eyes-potential-sale-valuation/",
      "published_at": "2026-01-13T15:43:49+00:00",
      "source": "cryptobriefing.com",
      "score": 1,
      "ntitle": "coingecko eyes potential sale valued at 500m"
    },
    {
      "title": "Fors Launches Beta to Aggregate Prediction Markets Across Solana Ecosystem",
      "link": "https://cryptopotato.com/fors-launches-beta-to-aggregate-prediction-markets-across-solana-ecosystem/",
      "published_at": "2026-01-13T16:15:03+00:00",
      "source": "cryptopotato.com",
      "score": 3,
      "ntitle": "fors launches beta aggregate prediction markets across solana ecosystem"
    },
    {
      "title": "The US Senate could wipe out $6 billion in crypto rewards this week by closing one specific loophole",
      "link": "https://cryptoslate.com/clarity-act-stablecoin-reward-definition-may-split-cryptos-coalition-after-genius-yield-ban-with-coinbase-hinting-at-revolt/",
      "published_at": "2026-01-13T14:25:52+00:00",
      "source": "cryptoslate.com",
      "score": 6,
      "ntitle": "us senate could wipe out 6 billion crypto rewards this week closing one specific loophole"
    },
    {
      "title": "Fors Launches Beta To Aggregate Prediction Markets Across Solana Ecosystem",
      "link": "https://dailyhodl.com/2026/01/13/fors-launches-beta-to-aggregate-prediction-markets-across-solana-ecosystem/",
      "published_at": "2026-01-13T16:01:08+00:00",
      "source": "dailyhodl.com",
      "score": 3,
      "ntitle": "fors launches beta aggregate prediction markets across solana ecosystem"
    },
    {
      "title": "Kraken-Linked SPAC Eyes $250 Million US Public Offering",
      "link": "https://decrypt.co/354410/kraken-linked-spac-eyes-250-million-us-public-offering",
      "published_at": "2026-01-13T16:18:16+00:00",
      "source": "decrypt.co",
      "score": 3,
      "ntitle": "kraken linked spac eyes 250 million us public offering"
    },
    {
      "title": "Agencies issue 2025 Shared National Credit Program report",
      "link": "https://www.federalreserve.gov/newsevents/pressreleases/bcreg20260112a.htm",
      "published_at": "2026-01-12T20:00:00+00:00",
      "source": "federalreserve.gov",
      "score": 1,
      "ntitle": "agencies issue 2025 shared national credit program report"
    },
    {
      "title": "Did Taylor Swift give UK GDP a big boost? Sorry, we still have no idea",
      "link": "https://www.ft.com/content/ae1a7b67-efda-4793-96be-40027483d1d2",
      "published_at": "2026-01-09T06:00:09+00:00",
      "source": "ft.com",
      "score": 5,
      "ntitle": "did taylor swift give uk gdp big boost sorry we still have no idea"
    },
    {
      "title": "BTC Market Pulse: Week 3",
      "link": "https://insights.glassnode.com/btc-market-pulse-week-3-2026/",
      "published_at": "2026-01-12T16:25:55+00:00",
      "source": "insights.glassnode.com",
      "score": 0,
      "ntitle": "btc market pulse week 3"
    },
    {
      "title": "Bitcoin price today: ticks up to $92.5k after cooler-than-expected core CPI data",
      "link": "https://www.investing.com/news/cryptocurrency-news/bitcoin-price-today-down-to-918k-as-sentiment-dithers-ahead-of-cpi-test-4443496",
      "published_at": "2026-01-13T15:26:47+00:00",
      "source": "investing.com",
      "score": 2,
      "ntitle": "bitcoin price today ticks up 92 5k after cooler than expected core cpi data"
    },
    {
      "title": "Crypto Twitter says Nikita Bier killed X — and ‘gm’",
      "link": "https://protos.com/crypto-twitter-says-nikita-bier-killed-x-and-gm/",
      "published_at": "2026-01-13T11:55:35+00:00",
      "source": "protos.com",
      "score": 1,
      "ntitle": "crypto twitter says nikita bier killed x gm"
    },
    {
      "title": "Paul Tzur and David Morrell Named Deputy Directors of the Division of Enforcement",
      "link": "https://www.sec.gov/newsroom/press-releases/2026-4-paul-tzur-david-morrell-named-deputy-directors-division-enforcement",
      "published_at": "2026-01-12T18:56:42+00:00",
      "source": "sec.gov",
      "score": 2,
      "ntitle": "paul tzur david morrell named deputy directors division enforcement"
    },
    {
      "title": "TD Bank Sees ‘Terrific Opportunities’ in Tokenized Deposits",
      "link": "https://thedefiant.io/news/tradfi-and-fintech/big-banks-explore-tokenized-deposits",
      "published_at": "2026-01-13T16:10:26+00:00",
      "source": "thedefiant.io",
      "score": 7,
      "ntitle": "td bank sees terrific opportunities tokenized deposits"
    },
    {
      "title": "Bitcoin (BTC) Price Analysis for January 13",
      "link": "https://u.today/bitcoin-btc-price-analysis-for-january-13",
      "published_at": "2026-01-13T15:52:00+00:00",
      "source": "u.today",
      "score": 1,
      "ntitle": "bitcoin btc price analysis january 13"
    },
    {
      "title": "Bitcoin and Ethereum Treasuries Expand as ETF Flows Turn Positive",
      "link": "https://unchainedcrypto.com/bitcoin-and-ethereum-treasuries-expand-as-etf-flows-turn-positive/",
      "published_at": "2026-01-13T12:31:39+00:00",
      "source": "unchainedcrypto.com",
      "score": 3,
      "ntitle": "bitcoin ethereum treasuries expand as etf flows turn positive"
    },
    {
      "title": "Common Security Risks in AI Systems — and How to Prevent Them",
      "link": "https://101blockchains.com/ai-security-risks/",
      "published_at": "2026-01-09T08:43:46+00:00",
      "source": "101blockchains.com",
      "score": 1,
      "ntitle": "common security risks ai systems how prevent them"
    },
    {
      "title": "BitMine Adds 24K ETH, Nears 4.2M Holdings",
      "link": "https://www.bankless.com/read/news/bitmine-adds-24k-eth-nears-4-2m-holdings",
      "published_at": "2026-01-12T15:49:35+00:00",
      "source": "bankless.com",
      "score": 1,
      "ntitle": "bitmine adds 24k eth nears 4 2m holdings"
    },
    {
      "title": "Bitcoin Price Briefly Jumps Above $92,800 As CPI Meets Forecasts, Powell DOJ Dispute Fuels Safe-Haven Bid",
      "link": "https://bitcoinmagazine.com/markets/bitcoin-price-jumps-above-92500",
      "published_at": "2026-01-13T15:04:14+00:00",
      "source": "bitcoinmagazine.com",
      "score": 2,
      "ntitle": "bitcoin price briefly jumps above 92 800 as cpi meets forecasts powell doj dispute fuels safe haven bid"
    },
    {
      "title": "Strategy Discloses $1.25 Billion Bitcoin Purchase Funded Through ATM Sales",
      "link": "https://btctimes.com/strategy-discloses-1-25-billion-bitcoin-purchase-funded-through-atm-sales/",
      "published_at": "2026-01-12T16:52:01+00:00",
      "source": "btctimes.com",
      "score": 1,
      "ntitle": "strategy discloses 1 25 billion bitcoin purchase funded through atm sales"
    },
    {
      "title": "Record $17 Billion Estimated Stolen in Crypto Scams and Fraud in 2025 as Impersonation Tactics and AI Enablement Surge",
      "link": "https://www.chainalysis.com/blog/crypto-scams-2026/",
      "published_at": "2026-01-13T12:34:05+00:00",
      "source": "chainalysis.com",
      "score": 2,
      "ntitle": "record 17 billion estimated stolen crypto scams fraud 2025 as impersonation tactics ai enablement surge"
    },
    {
      "title": "10 Best AI Sales Tools to Boost Performance",
      "link": "https://coincodecap.com/best-ai-sales-tools-to-boost-performance?utm_source=rss&utm_medium=rss&utm_campaign=best-ai-sales-tools-to-boost-performance",
      "published_at": "2026-01-13T11:32:17+00:00",
      "source": "coincodecap.com",
      "score": 3,
      "ntitle": "10 best ai sales tools boost performance"
    },
    {
      "title": "WIF price reclaims 200-day moving average",
      "link": "https://crypto.news/wif-price-reclaims-200-day-moving-average/",
      "published_at": "2026-01-13T15:44:29+00:00",
      "source": "crypto.news",
      "score": 1,
      "ntitle": "wif price reclaims 200 day moving average"
    }
  ],
  "month": [
    {
      "title": "Blockchain Security Basics for Business Leaders",
      "link": "https://101blockchains.com/blockchain-security-for-business-leaders/",
      "published_at": "2026-01-07T08:52:26+00:00",
      "source": "101blockchains.com",
      "score": 1,
      "ntitle": "blockchain security basics business leaders"
    },
    {
      "title": "Senators Meet to Discuss Crypto Market Structure Bill",
      "link": "https://www.bankless.com/read/news/senators-meet-to-discuss-crypto-market-structure-bill",
      "published_at": "2026-01-06T19:49:49+00:00",
      "source": "bankless.com",
      "score": 1,
      "ntitle": "senators meet discuss crypto market structure bill"
    },
    {
      "title": "Venezuela’s sanctions are stablecoins’ proof of concept",
      "link": "https://blockworks.co/news/venezuelas-sanctions-stablecoins",
      "published_at": "2026-01-07T14:00:00+00:00",
      "source": "blockworks.co",
      "score": 1,
      "ntitle": "venezuela s sanctions stablecoins proof concept"
    },
    {
      "title": "Bank of America Allows up to 4% Spot Bitcoin ETF Allocations",
      "link": "https://btctimes.com/bank-of-america-allows-up-to-4-spot-bitcoin-etf-allocations/",
      "published_at": "2026-01-06T15:53:04+00:00",
      "source": "btctimes.com",
      "score": 5,
      "ntitle": "bank america allows up 4 spot bitcoin etf allocations"
    },
    {
      "title": "An Introduction to Perpetual Futures",
      "link": "https://www.chainalysis.com/blog/perpetual-futures/",
      "published_at": "2026-01-06T16:12:51+00:00",
      "source": "chainalysis.com",
      "score": 0,
      "ntitle": "introduction perpetual futures"
    },
    {
      "title": "Movers & Shakers January 2026",
      "link": "https://coinmetrics.io/general-research/movers-shakers-january-2026/",
      "published_at": "2026-01-06T19:06:25+00:00",
      "source": "coinmetrics.io",
      "score": 0,
      "ntitle": "movers shakers january 2026"
    },
    {
      "title": "First 2026 Dip! BTC at 92K! Morgan Stanley file for BTC, ETH & SOL ETFs! Hyperliquid Airdrop Speculation!",
      "link": "https://decrypt.co/videos/interviews/GVQVX2ND/first-2026-dip-btc-at-92k-morgan-stanley-file-for-btc-eth-sol-etfs-hyperliquid-airdrop-speculation",
      "published_at": "2026-01-07T16:14:54+00:00",
      "source": "decrypt.co",
      "score": 11,
      "ntitle": "first 2026 dip btc at 92k morgan stanley file btc eth sol etfs hyperliquid airdrop speculation"
    },
    {
      "title": "Minutes of the Board's discount rate meeting on December 10, 2025",
      "link": "https://www.federalreserve.gov/newsevents/pressreleases/monetary20260106a.htm",
      "published_at": "2026-01-06T19:00:00+00:00",
      "source": "federalreserve.gov",
      "score": 1,
      "ntitle": "minutes board s discount rate meeting december 10 2025"
    },
    {
      "title": "The Altcoin Vector #36",
      "link": "https://insights.glassnode.com/the-altcoin-vector-36/",
      "published_at": "2026-01-07T12:02:48+00:00",
      "source": "insights.glassnode.com",
      "score": 0,
      "ntitle": "altcoin vector 36"
    },
    {
      "title": "Deputy Director of Enforcement Nekia Hackworth Jones Concludes Her Tenure at the SEC",
      "link": "https://www.sec.gov/newsroom/press-releases/2025-146-deputy-director-enforcement-nekia-hackworth-jones-concludes-her-tenure-sec",
      "published_at": "2025-12-29T18:36:34+00:00",
      "source": "sec.gov",
      "score": 2,
      "ntitle": "deputy director enforcement nekia hackworth jones concludes her tenure at sec"
    },
    {
      "title": "J.P. Morgan’s Deposit Token to Be Issued Natively on Canton Network",
      "link": "https://thedefiant.io/news/defi/j-p-morgan-s-deposit-token-to-be-issued-natively-on-canton-network",
      "published_at": "2026-01-07T13:00:13+00:00",
      "source": "thedefiant.io",
      "score": 1,
      "ntitle": "j p morgan s deposit token be issued natively canton network"
    },
    {
      "title": "Success Story: Tomas Chatila’s Learning Journey with 101 Blockchains",
      "link": "https://101blockchains.com/tomas-chatila-success-story/",
      "published_at": "2026-01-05T08:42:43+00:00",
      "source": "101blockchains.com",
      "score": 1,
      "ntitle": "success story tomas chatila s learning journey 101 blockchains"
    },
    {
      "title": "Brian Quintenz Joins SUI Group After CFTC Nomination Falls Short",
      "link": "https://www.bankless.com/read/news/brian-quintenz-joins-sui-group-after-cftc-nomination-falls-short",
      "published_at": "2026-01-06T18:06:18+00:00",
      "source": "bankless.com",
      "score": 1,
      "ntitle": "brian quintenz joins sui group after cftc nomination falls short"
    },
    {
      "title": "The Strategy playbook looks different in 2026",
      "link": "https://blockworks.co/news/strategy-playbook-2026",
      "published_at": "2026-01-06T17:36:33+00:00",
      "source": "blockworks.co",
      "score": 3,
      "ntitle": "strategy playbook looks different 2026"
    },
    {
      "title": "Strategy Reports $116 Million Bitcoin Purchase To Start 2026",
      "link": "https://btctimes.com/strategy-reports-116-million-bitcoin-purchase-to-start-2026/",
      "published_at": "2026-01-05T23:33:04+00:00",
      "source": "btctimes.com",
      "score": 1,
      "ntitle": "strategy reports 116 million bitcoin purchase start 2026"
    },
    {
      "title": "How IRS-CI Follows The Crypto: Podcast Ep. 176",
      "link": "https://www.chainalysis.com/blog/how-irs-ci-follows-the-crypto-ep-176/",
      "published_at": "2025-12-30T09:31:37+00:00",
      "source": "chainalysis.com",
      "score": 1,
      "ntitle": "how irs ci follows crypto podcast ep 176"
    },
    {
      "title": "Crypto’s Constructive Start to 2026",
      "link": "https://coinmetrics.io/state-of-the-network/cryptos-constructive-start-to-2026/",
      "published_at": "2026-01-06T13:49:28+00:00",
      "source": "coinmetrics.io",
      "score": 2,
      "ntitle": "crypto s constructive start 2026"
    },
    {
      "title": "Crypto starts 2026 STRONG! Venezuela Impacts on the market! Lighter TGE reactions!",
      "link": "https://decrypt.co/videos/interviews/XjhRjGIk/crypto-starts-2026-strong-venezuela-impacts-on-the-market-lighter-tge-reactions",
      "published_at": "2026-01-06T18:16:42+00:00",
      "source": "decrypt.co",
      "score": 15,
      "ntitle": "crypto starts 2026 strong venezuela impacts market lighter tge reactions"
    },
    {
      "title": "Federal Reserve Board issues enforcement action with former employee of Regions Bank",
      "link": "https://www.federalreserve.gov/newsevents/pressreleases/enforcement20260106a.htm",
      "published_at": "2026-01-06T16:00:00+00:00",
      "source": "federalreserve.gov",
      "score": 4,
      "ntitle": "federal reserve board issues enforcement action former employee regions bank"
    },
    {
      "title": "The Bitcoin Vector #37",
      "link": "https://insights.glassnode.com/the-bitcoin-vector-37/",
      "published_at": "2026-01-07T11:57:11+00:00",
      "source": "insights.glassnode.com",
      "score": 0,
      "ntitle": "bitcoin vector 37"
    },
    {
      "title": "SEC Announces Retirement of Division of Corporation Finance Deputy Director Cicely LaMothe",
      "link": "https://www.sec.gov/newsroom/press-releases/2025-145-sec-announces-retirement-division-corporation-finance-deputy-director-cicely-lamothe",
      "published_at": "2025-12-29T16:45:00+00:00",
      "source": "sec.gov",
      "score": 2,
      "ntitle": "sec announces retirement division corporation finance deputy director cicely lamothe"
    },
    {
      "title": "Investors Eye Venezuela’s Bitcoin Stash Following Maduro’s Capture",
      "link": "https://thedefiant.io/news/markets/investors-eye-venezuela-s-bitcoin-stash-following-maduro-s-capture",
      "published_at": "2026-01-06T23:10:13+00:00",
      "source": "thedefiant.io",
      "score": 1,
      "ntitle": "investors eye venezuela s bitcoin stash following maduro s capture"
    }
  ],
  "generated_at": "2026-01-14T16:25:42.832323+00:00"
}