{
  "prices": [
    {
      "rank": 1,
      "symbol": "btc",
      "price": 91335,
      "change24h": 1.13257
    },
    {
      "rank": 2,
      "symbol": "eth",
      "price": 3144.62,
      "change24h": 1.01609
    },
    {
      "rank": 3,
      "symbol": "usdt",
      "price": 0.999653,
      "change24h": 0.00908
    },
    {
      "rank": 4,
      "symbol": "xrp",
      "price": 2.1,
      "change24h": 4.56525
    },
    {
      "rank": 5,
      "symbol": "bnb",
      "price": 896.09,
      "change24h": 2.16364
    },
    {
      "rank": 6,
      "symbol": "sol",
      "price": 134.27,
      "change24h": 1.77742
    },
    {
      "rank": 7,
      "symbol": "usdc",
      "price": 0.999974,
      "change24h": 0.01104
    },
    {
      "rank": 8,
      "symbol": "trx",
      "price": 0.293751,
      "change24h": -0.05872
    },
    {
      "rank": 9,
      "symbol": "steth",
      "price": 3142.08,
      "change24h": 0.99542
    },
    {
      "rank": 10,
      "symbol": "doge",
      "price": 0.150313,
      "change24h": 5.59736
    },
    {
      "rank": 11,
      "symbol": "figr_heloc",
      "price": 1.019,
      "change24h": 0.0
    },
    {
      "rank": 12,
      "symbol": "ada",
      "price": 0.400424,
      "change24h": 3.35794
    },
    {
      "rank": 13,
      "symbol": "bch",
      "price": 641.2,
      "change24h": -2.38717
    },
    {
      "rank": 14,
      "symbol": "wsteth",
      "price": 3847.31,
      "change24h": 1.05323
    },
    {
      "rank": 15,
      "symbol": "wbt",
      "price": 57.7,
      "change24h": 0.75548
    },
    {
      "rank": 16,
      "symbol": "wbtc",
      "price": 91243,
      "change24h": 1.19288
    },
    {
      "rank": 17,
      "symbol": "wbeth",
      "price": 3418.07,
      "change24h": 1.06284
    },
    {
      "rank": 18,
      "symbol": "weeth",
      "price": 3411.67,
      "change24h": 1.03961
    },
    {
      "rank": 19,
      "symbol": "usds",
      "price": 0.999542,
      "change24h": -0.02257
    },
    {
      "rank": 20,
      "symbol": "link",
      "price": 13.44,
      "change24h": 2.01267
    },
    {
      "rank": 21,
      "symbol": "bsc-usd",
      "price": 0.999288,
      "change24h": -0.01127
    },
    {
      "rank": 22,
      "symbol": "zec",
      "price": 504.25,
      "change24h": -0.46468
    },
    {
      "rank": 23,
      "symbol": "leo",
      "price": 8.93,
      "change24h": -3.68183
    },
    {
      "rank": 24,
      "symbol": "weth",
      "price": 3145.27,
      "change24h": 1.0384
    },
    {
      "rank": 25,
      "symbol": "xmr",
      "price": 421.42,
      "change24h": -3.26495
    },
    {
      "rank": 26,
      "symbol": "xlm",
      "price": 0.233579,
      "change24h": 6.34482
    },
    {
      "rank": 27,
      "symbol": "cbbtc",
      "price": 91346,
      "change24h": 1.14403
    },
    {
      "rank": 28,
      "symbol": "sui",
      "price": 1.72,
      "change24h": 4.48098
    },
    {
      "rank": 29,
      "symbol": "usde",
      "price": 0.999758,
      "change24h": 0.02393
    },
    {
      "rank": 30,
      "symbol": "hype",
      "price": 26.53,
      "change24h": 7.1444
    },
    {
      "rank": 31,
      "symbol": "ltc",
      "price": 82.21,
      "change24h": -0.15471
    },
    {
      "rank": 32,
      "symbol": "avax",
      "price": 14.28,
      "change24h": 2.89482
    },
    {
      "rank": 33,
      "symbol": "cc",
      "price": 0.150165,
      "change24h": -4.75125
    },
    {
      "rank": 34,
      "symbol": "hbar",
      "price": 0.126008,
      "change24h": 5.17512
    },
    {
      "rank": 35,
      "symbol": "shib",
      "price": 9.06e-06,
      "change24h": 12.94753
    },
    {
      "rank": 36,
      "symbol": "wlfi",
      "price": 0.170302,
      "change24h": -4.41401
    },
    {
      "rank": 37,
      "symbol": "susds",
      "price": 1.082,
      "change24h": -0.08649
    },
    {
      "rank": 38,
      "symbol": "ton",
      "price": 1.86,
      "change24h": 0.52697
    },
    {
      "rank": 39,
      "symbol": "usdt0",
      "price": 0.999213,
      "change24h": -0.01302
    },
    {
      "rank": 40,
      "symbol": "dai",
      "price": 0.999464,
      "change24h": -0.008
    },
    {
      "rank": 41,
      "symbol": "cro",
      "price": 0.105539,
      "change24h": 6.21204
    },
    {
      "rank": 42,
      "symbol": "uni",
      "price": 5.88,
      "change24h": -0.15924
    },
    {
      "rank": 43,
      "symbol": "pyusd",
      "price": 0.999935,
      "change24h": 0.01075
    },
    {
      "rank": 44,
      "symbol": "dot",
      "price": 2.15,
      "change24h": 0.95405
    },
    {
      "rank": 45,
      "symbol": "susde",
      "price": 1.21,
      "change24h": -0.00011
    },
    {
      "rank": 46,
      "symbol": "mnt",
      "price": 1.057,
      "change24h": 6.88092
    },
    {
      "rank": 47,
      "symbol": "usd1",
      "price": 1.0,
      "change24h": -0.01104
    },
    {
      "rank": 48,
      "symbol": "pepe",
      "price": 7.12e-06,
      "change24h": 16.31689
    },
    {
      "rank": 49,
      "symbol": "rain",
      "price": 0.00800375,
      "change24h": -0.11006
    },
    {
      "rank": 50,
      "symbol": "m",
      "price": 1.58,
      "change24h": -1.87647
    },
    {
      "rank": 51,
      "symbol": "tao",
      "price": 265.04,
      "change24h": 5.35558
    },
    {
      "rank": 52,
      "symbol": "bgb",
      "price": 3.57,
      "change24h": 0.84203
    },
    {
      "rank": 53,
      "symbol": "aave",
      "price": 164.45,
      "change24h": 2.10289
    },
    {
      "rank": 54,
      "symbol": "okb",
      "price": 113.65,
      "change24h": 0.39359
    },
    {
      "rank": 55,
      "symbol": "xaut",
      "price": 4363.56,
      "change24h": 0.35491
    },
    {
      "rank": 56,
      "symbol": "near",
      "price": 1.73,
      "change24h": 1.7401
    },
    {
      "rank": 57,
      "symbol": "usdf",
      "price": 0.997842,
      "change24h": -0.00831
    },
    {
      "rank": 58,
      "symbol": "etc",
      "price": 12.81,
      "change24h": 2.60151
    },
    {
      "rank": 59,
      "symbol": "jitosol",
      "price": 168.06,
      "change24h": 1.73897
    },
    {
      "rank": 60,
      "symbol": "ena",
      "price": 0.248573,
      "change24h": 5.76701
    },
    {
      "rank": 61,
      "symbol": "weth",
      "price": 3143.88,
      "change24h": 1.00294
    },
    {
      "rank": 62,
      "symbol": "aster",
      "price": 0.783855,
      "change24h": 5.57892
    },
    {
      "rank": 63,
      "symbol": "icp",
      "price": 3.27,
      "change24h": 5.58162
    },
    {
      "rank": 64,
      "symbol": "pi",
      "price": 0.212922,
      "change24h": 2.10363
    },
    {
      "rank": 65,
      "symbol": "buidl",
      "price": 1.0,
      "change24h": 0.0
    },
    {
      "rank": 66,
      "symbol": "sol",
      "price": 134.15,
      "change24h": 1.68279
    },
    {
      "rank": 67,
      "symbol": "paxg",
      "price": 4375.54,
      "change24h": 0.437
    },
    {
      "rank": 68,
      "symbol": "wld",
      "price": 0.59872,
      "change24h": 4.33881
    },
    {
      "rank": 69,
      "symbol": "htx",
      "price": 1.69e-06,
      "change24h": 0.65467
    },
    {
      "rank": 70,
      "symbol": "hash",
      "price": 0.02948596,
      "change24h": -4.59591
    },
    {
      "rank": 71,
      "symbol": "usdg",
      "price": 0.999671,
      "change24h": 0.0026
    },
    {
      "rank": 72,
      "symbol": "jlp",
      "price": 4.71,
      "change24h": 0.98516
    },
    {
      "rank": 73,
      "symbol": "usyc",
      "price": 1.11,
      "change24h": null
    },
    {
      "rank": 74,
      "symbol": "night",
      "price": 0.089589,
      "change24h": -2.54898
    },
    {
      "rank": 75,
      "symbol": "kcs",
      "price": 11.1,
      "change24h": 0.81045
    },
    {
      "rank": 76,
      "symbol": "apt",
      "price": 1.93,
      "change24h": 1.55693
    },
    {
      "rank": 77,
      "symbol": "bnsol",
      "price": 146.63,
      "change24h": 1.83622
    },
    {
      "rank": 78,
      "symbol": "sky",
      "price": 0.06206,
      "change24h": 0.21676
    },
    {
      "rank": 79,
      "symbol": "syrupusdc",
      "price": 1.14,
      "change24h": 0.01447
    },
    {
      "rank": 80,
      "symbol": "ondo",
      "price": 0.438671,
      "change24h": 3.79944
    },
    {
      "rank": 81,
      "symbol": "pump",
      "price": 0.00234172,
      "change24h": 3.17416
    },
    {
      "rank": 82,
      "symbol": "rlusd",
      "price": 0.99996,
      "change24h": 0.00223
    },
    {
      "rank": 83,
      "symbol": "kas",
      "price": 0.04997128,
      "change24h": 10.91685
    },
    {
      "rank": 84,
      "symbol": "bfusd",
      "price": 0.999243,
      "change24h": 0.00121
    },
    {
      "rank": 85,
      "symbol": "reth",
      "price": 3630.51,
      "change24h": 1.06646
    },
    {
      "rank": 86,
      "symbol": "wbnb",
      "price": 895.84,
      "change24h": 2.16563
    },
    {
      "rank": 87,
      "symbol": "usdc",
      "price": 0.999511,
      "change24h": -0.02556
    },
    {
      "rank": 88,
      "symbol": "pol",
      "price": 0.12164,
      "change24h": 6.11491
    },
    {
      "rank": 89,
      "symbol": "gt",
      "price": 10.57,
      "change24h": 0.97632
    },
    {
      "rank": 90,
      "symbol": "arb",
      "price": 0.215235,
      "change24h": 3.64995
    },
    {
      "rank": 91,
      "symbol": "algo",
      "price": 0.135885,
      "change24h": 7.11298
    },
    {
      "rank": 92,
      "symbol": "rseth",
      "price": 3339.1,
      "change24h": 1.03424
    },
    {
      "rank": 93,
      "symbol": "qnt",
      "price": 78.35,
      "change24h": -1.22599
    },
    {
      "rank": 94,
      "symbol": "atom",
      "price": 2.32,
      "change24h": 4.38528
    },
    {
      "rank": 95,
      "symbol": "myx",
      "price": 5.89,
      "change24h": -6.51531
    },
    {
      "rank": 96,
      "symbol": "fil",
      "price": 1.49,
      "change24h": 0.41397
    },
    {
      "rank": 97,
      "symbol": "trump",
      "price": 5.4,
      "change24h": 2.00952
    },
    {
      "rank": 98,
      "symbol": "bonk",
      "price": 1.21e-05,
      "change24h": 33.14446
    },
    {
      "rank": 99,
      "symbol": "vet",
      "price": 0.01208555,
      "change24h": 3.92012
    },
    {
      "rank": 100,
      "symbol": "jaaa",
      "price": 1.021,
      "change24h": 0.06253
    },
    {
      "rank": 101,
      "symbol": "wsteth",
      "price": 3836.47,
      "change24h": 0.94482
    },
    {
      "rank": 102,
      "symbol": "fbtc",
      "price": 91822,
      "change24h": 2.47233
    },
    {
      "rank": 103,
      "symbol": "render",
      "price": 1.94,
      "change24h": 12.97094
    },
    {
      "rank": 104,
      "symbol": "lbtc",
      "price": 91627,
      "change24h": 1.62842
    },
    {
      "rank": 105,
      "symbol": "xdc",
      "price": 0.05159,
      "change24h": -1.18372
    },
    {
      "rank": 106,
      "symbol": "solvbtc",
      "price": 90809,
      "change24h": 0.58573
    },
    {
      "rank": 107,
      "symbol": "flr",
      "price": 0.01163104,
      "change24h": 6.03605
    },
    {
      "rank": 108,
      "symbol": "nexo",
      "price": 0.948336,
      "change24h": 0.723
    },
    {
      "rank": 109,
      "symbol": "usdd",
      "price": 0.999571,
      "change24h": 0.01322
    },
    {
      "rank": 110,
      "symbol": "lseth",
      "price": 3346.86,
      "change24h": 0.72211
    },
    {
      "rank": 111,
      "symbol": "usdtb",
      "price": 0.999705,
      "change24h": -0.00474
    },
    {
      "rank": 112,
      "symbol": "ousg",
      "price": 113.85,
      "change24h": 0.0
    },
    {
      "rank": 113,
      "symbol": "ustb",
      "price": 10.94,
      "change24h": 0.0
    },
    {
      "rank": 114,
      "symbol": "sei",
      "price": 0.124368,
      "change24h": 2.91655
    },
    {
      "rank": 115,
      "symbol": "pengu",
      "price": 0.01260084,
      "change24h": 16.80353
    },
    {
      "rank": 116,
      "symbol": "wm",
      "price": 0.999574,
      "change24h": -0.00385
    },
    {
      "rank": 117,
      "symbol": "usdc.e",
      "price": 0.999604,
      "change24h": -0.01031
    },
    {
      "rank": 118,
      "symbol": "ip",
      "price": 2.16,
      "change24h": 3.7942
    },
    {
      "rank": 119,
      "symbol": "wbtc",
      "price": 91190,
      "change24h": 1.11734
    },
    {
      "rank": 120,
      "symbol": "meth",
      "price": 3403.25,
      "change24h": 1.12152
    },
    {
      "rank": 121,
      "symbol": "ezeth",
      "price": 3356.58,
      "change24h": 0.96357
    },
    {
      "rank": 122,
      "symbol": "clbtc",
      "price": 90486,
      "change24h": -0.00376
    },
    {
      "rank": 123,
      "symbol": "syrupusdt",
      "price": 1.11,
      "change24h": 0.06645
    },
    {
      "rank": 124,
      "symbol": "bdx",
      "price": 0.091197,
      "change24h": -2.53092
    },
    {
      "rank": 125,
      "symbol": "cake",
      "price": 2.06,
      "change24h": 3.40553
    }
  ],
  "gainers": [
    {
      "symbol": "bonk",
      "price": 1.21e-05,
      "change24h": 33.14446
    },
    {
      "symbol": "pengu",
      "price": 0.01260084,
      "change24h": 16.80353
    },
    {
      "symbol": "pepe",
      "price": 7.12e-06,
      "change24h": 16.31689
    },
    {
      "symbol": "render",
      "price": 1.94,
      "change24h": 12.97094
    },
    {
      "symbol": "shib",
      "price": 9.06e-06,
      "change24h": 12.94753
    },
    {
      "symbol": "kas",
      "price": 0.04997128,
      "change24h": 10.91685
    },
    {
      "symbol": "hype",
      "price": 26.53,
      "change24h": 7.1444
    },
    {
      "symbol": "algo",
      "price": 0.135885,
      "change24h": 7.11298
    },
    {
      "symbol": "mnt",
      "price": 1.057,
      "change24h": 6.88092
    },
    {
      "symbol": "xlm",
      "price": 0.233579,
      "change24h": 6.34482
    },
    {
      "symbol": "cro",
      "price": 0.105539,
      "change24h": 6.21204
    },
    {
      "symbol": "pol",
      "price": 0.12164,
      "change24h": 6.11491
    },
    {
      "symbol": "flr",
      "price": 0.01163104,
      "change24h": 6.03605
    },
    {
      "symbol": "ena",
      "price": 0.248573,
      "change24h": 5.76701
    },
    {
      "symbol": "doge",
      "price": 0.150313,
      "change24h": 5.59736
    }
  ],
  "losers": [
    {
      "symbol": "myx",
      "price": 5.89,
      "change24h": -6.51531
    },
    {
      "symbol": "cc",
      "price": 0.150165,
      "change24h": -4.75125
    },
    {
      "symbol": "hash",
      "price": 0.02948596,
      "change24h": -4.59591
    },
    {
      "symbol": "wlfi",
      "price": 0.170302,
      "change24h": -4.41401
    },
    {
      "symbol": "leo",
      "price": 8.93,
      "change24h": -3.68183
    },
    {
      "symbol": "xmr",
      "price": 421.42,
      "change24h": -3.26495
    },
    {
      "symbol": "night",
      "price": 0.089589,
      "change24h": -2.54898
    },
    {
      "symbol": "bdx",
      "price": 0.091197,
      "change24h": -2.53092
    },
    {
      "symbol": "bch",
      "price": 641.2,
      "change24h": -2.38717
    },
    {
      "symbol": "m",
      "price": 1.58,
      "change24h": -1.87647
    },
    {
      "symbol": "qnt",
      "price": 78.35,
      "change24h": -1.22599
    },
    {
      "symbol": "xdc",
      "price": 0.05159,
      "change24h": -1.18372
    },
    {
      "symbol": "zec",
      "price": 504.25,
      "change24h": -0.46468
    },
    {
      "symbol": "uni",
      "price": 5.88,
      "change24h": -0.15924
    },
    {
      "symbol": "ltc",
      "price": 82.21,
      "change24h": -0.15471
    }
  ]
}