{
  "prices": [
    {
      "rank": 1,
      "symbol": "btc",
      "price": 111246,
      "change24h": 0.90224
    },
    {
      "rank": 2,
      "symbol": "eth",
      "price": 4291.25,
      "change24h": 0.43175
    },
    {
      "rank": 3,
      "symbol": "xrp",
      "price": 2.89,
      "change24h": 2.89365
    },
    {
      "rank": 4,
      "symbol": "usdt",
      "price": 1.0,
      "change24h": -0.02228
    },
    {
      "rank": 5,
      "symbol": "bnb",
      "price": 873.3,
      "change24h": 1.40621
    },
    {
      "rank": 6,
      "symbol": "sol",
      "price": 204.11,
      "change24h": 1.13754
    },
    {
      "rank": 7,
      "symbol": "usdc",
      "price": 0.999811,
      "change24h": -0.00493
    },
    {
      "rank": 8,
      "symbol": "steth",
      "price": 4283.97,
      "change24h": 0.41943
    },
    {
      "rank": 9,
      "symbol": "doge",
      "price": 0.222892,
      "change24h": 3.81451
    },
    {
      "rank": 10,
      "symbol": "trx",
      "price": 0.329318,
      "change24h": 0.70897
    },
    {
      "rank": 11,
      "symbol": "ada",
      "price": 0.831599,
      "change24h": 0.95064
    },
    {
      "rank": 12,
      "symbol": "wsteth",
      "price": 5198.41,
      "change24h": 0.38837
    },
    {
      "rank": 13,
      "symbol": "link",
      "price": 22.31,
      "change24h": 0.49808
    },
    {
      "rank": 14,
      "symbol": "wbeth",
      "price": 4621.29,
      "change24h": 0.36738
    },
    {
      "rank": 15,
      "symbol": "wbtc",
      "price": 111256,
      "change24h": 0.92553
    },
    {
      "rank": 16,
      "symbol": "hype",
      "price": 47.34,
      "change24h": 2.51887
    },
    {
      "rank": 17,
      "symbol": "usde",
      "price": 1.001,
      "change24h": -0.00561
    },
    {
      "rank": 18,
      "symbol": "figr_heloc",
      "price": 1.0,
      "change24h": -0.46212
    },
    {
      "rank": 19,
      "symbol": "sui",
      "price": 3.39,
      "change24h": 1.37678
    },
    {
      "rank": 20,
      "symbol": "bch",
      "price": 602.79,
      "change24h": 1.06232
    },
    {
      "rank": 21,
      "symbol": "weeth",
      "price": 4609.27,
      "change24h": 0.53776
    },
    {
      "rank": 22,
      "symbol": "xlm",
      "price": 0.361276,
      "change24h": 1.4239
    },
    {
      "rank": 23,
      "symbol": "avax",
      "price": 24.49,
      "change24h": 0.11378
    },
    {
      "rank": 24,
      "symbol": "weth",
      "price": 4291.23,
      "change24h": 0.49563
    },
    {
      "rank": 25,
      "symbol": "hbar",
      "price": 0.219583,
      "change24h": 1.8358
    },
    {
      "rank": 26,
      "symbol": "leo",
      "price": 9.55,
      "change24h": -0.09069
    },
    {
      "rank": 27,
      "symbol": "ltc",
      "price": 114.49,
      "change24h": 2.06874
    },
    {
      "rank": 28,
      "symbol": "cro",
      "price": 0.259665,
      "change24h": -3.50608
    },
    {
      "rank": 29,
      "symbol": "usds",
      "price": 0.999933,
      "change24h": 0.00695
    },
    {
      "rank": 30,
      "symbol": "ton",
      "price": 3.09,
      "change24h": 1.08887
    },
    {
      "rank": 31,
      "symbol": "shib",
      "price": 1.241e-05,
      "change24h": 1.483
    },
    {
      "rank": 32,
      "symbol": "bsc-usd",
      "price": 1.0,
      "change24h": 0.06525
    },
    {
      "rank": 33,
      "symbol": "cbbtc",
      "price": 111233,
      "change24h": 0.92835
    },
    {
      "rank": 34,
      "symbol": "wbt",
      "price": 42.3,
      "change24h": 0.31598
    },
    {
      "rank": 35,
      "symbol": "dot",
      "price": 3.98,
      "change24h": 4.68755
    },
    {
      "rank": 36,
      "symbol": "wlfi",
      "price": 0.222232,
      "change24h": 12.63823
    },
    {
      "rank": 37,
      "symbol": "susde",
      "price": 1.2,
      "change24h": -0.02277
    },
    {
      "rank": 38,
      "symbol": "uni",
      "price": 9.33,
      "change24h": 0.323
    },
    {
      "rank": 39,
      "symbol": "ena",
      "price": 0.746516,
      "change24h": 1.57809
    },
    {
      "rank": 40,
      "symbol": "xmr",
      "price": 272.69,
      "change24h": 2.1912
    },
    {
      "rank": 41,
      "symbol": "aave",
      "price": 299.61,
      "change24h": -0.33236
    },
    {
      "rank": 42,
      "symbol": "dai",
      "price": 1.0,
      "change24h": 0.01896
    },
    {
      "rank": 43,
      "symbol": "bgb",
      "price": 4.84,
      "change24h": 1.0953
    },
    {
      "rank": 44,
      "symbol": "pepe",
      "price": 9.88e-06,
      "change24h": 2.69678
    },
    {
      "rank": 45,
      "symbol": "okb",
      "price": 196.5,
      "change24h": 1.35193
    },
    {
      "rank": 46,
      "symbol": "mnt",
      "price": 1.15,
      "change24h": -0.79829
    },
    {
      "rank": 47,
      "symbol": "m",
      "price": 1.89,
      "change24h": 8.96946
    },
    {
      "rank": 48,
      "symbol": "tao",
      "price": 327.17,
      "change24h": 3.64567
    },
    {
      "rank": 49,
      "symbol": "etc",
      "price": 20.39,
      "change24h": 0.98505
    },
    {
      "rank": 50,
      "symbol": "near",
      "price": 2.47,
      "change24h": 2.82811
    },
    {
      "rank": 51,
      "symbol": "jitosol",
      "price": 250.64,
      "change24h": 1.12218
    },
    {
      "rank": 52,
      "symbol": "apt",
      "price": 4.27,
      "change24h": 1.41424
    },
    {
      "rank": 53,
      "symbol": "pol",
      "price": 0.275412,
      "change24h": -0.30274
    },
    {
      "rank": 54,
      "symbol": "ondo",
      "price": 0.909426,
      "change24h": 0.84869
    },
    {
      "rank": 55,
      "symbol": "usdt0",
      "price": 0.999712,
      "change24h": -0.05955
    },
    {
      "rank": 56,
      "symbol": "pi",
      "price": 0.343835,
      "change24h": 0.93425
    },
    {
      "rank": 57,
      "symbol": "usd1",
      "price": 0.999204,
      "change24h": 0.0247
    },
    {
      "rank": 58,
      "symbol": "arb",
      "price": 0.490345,
      "change24h": 0.64291
    },
    {
      "rank": 59,
      "symbol": "weth",
      "price": 4289.51,
      "change24h": 0.44302
    },
    {
      "rank": 60,
      "symbol": "icp",
      "price": 4.81,
      "change24h": 1.50817
    },
    {
      "rank": 61,
      "symbol": "ip",
      "price": 8.22,
      "change24h": 2.14247
    },
    {
      "rank": 62,
      "symbol": "bnsol",
      "price": 218.88,
      "change24h": 1.18158
    },
    {
      "rank": 63,
      "symbol": "buidl",
      "price": 1.0,
      "change24h": 0.0
    },
    {
      "rank": 64,
      "symbol": "kas",
      "price": 0.079895,
      "change24h": 3.13906
    },
    {
      "rank": 65,
      "symbol": "wld",
      "price": 1.044,
      "change24h": 14.36702
    },
    {
      "rank": 66,
      "symbol": "atom",
      "price": 4.46,
      "change24h": 1.68858
    },
    {
      "rank": 67,
      "symbol": "susds",
      "price": 1.067,
      "change24h": 0.07908
    },
    {
      "rank": 68,
      "symbol": "vet",
      "price": 0.0235308,
      "change24h": 1.12296
    },
    {
      "rank": 69,
      "symbol": "jlp",
      "price": 5.42,
      "change24h": 0.54538
    },
    {
      "rank": 70,
      "symbol": "gt",
      "price": 16.86,
      "change24h": -0.08158
    },
    {
      "rank": 71,
      "symbol": "algo",
      "price": 0.230175,
      "change24h": 1.52516
    },
    {
      "rank": 72,
      "symbol": "reth",
      "price": 4894.76,
      "change24h": 0.50054
    },
    {
      "rank": 73,
      "symbol": "ftn",
      "price": 4.5,
      "change24h": 0.09973
    },
    {
      "rank": 74,
      "symbol": "khype",
      "price": 47.39,
      "change24h": 2.34286
    },
    {
      "rank": 75,
      "symbol": "rseth",
      "price": 4512.34,
      "change24h": 0.40366
    },
    {
      "rank": 76,
      "symbol": "pengu",
      "price": 0.02899685,
      "change24h": 0.72339
    },
    {
      "rank": 77,
      "symbol": "kcs",
      "price": 14.26,
      "change24h": 0.20447
    },
    {
      "rank": 78,
      "symbol": "render",
      "price": 3.48,
      "change24h": 1.99336
    },
    {
      "rank": 79,
      "symbol": "sei",
      "price": 0.295103,
      "change24h": 3.36495
    },
    {
      "rank": 80,
      "symbol": "bfusd",
      "price": 0.999418,
      "change24h": -0.02066
    },
    {
      "rank": 81,
      "symbol": "pump",
      "price": 0.00482596,
      "change24h": 5.18698
    },
    {
      "rank": 82,
      "symbol": "trump",
      "price": 8.45,
      "change24h": 1.54496
    },
    {
      "rank": 83,
      "symbol": "sky",
      "price": 0.07123,
      "change24h": -2.77757
    },
    {
      "rank": 84,
      "symbol": "usdf",
      "price": 0.999674,
      "change24h": 0.07285
    },
    {
      "rank": 85,
      "symbol": "fil",
      "price": 2.38,
      "change24h": 2.30876
    },
    {
      "rank": 86,
      "symbol": "fet",
      "price": 0.626133,
      "change24h": 4.21108
    },
    {
      "rank": 87,
      "symbol": "oseth",
      "price": 4522.06,
      "change24h": 0.56715
    },
    {
      "rank": 88,
      "symbol": "flr",
      "price": 0.02173933,
      "change24h": 4.17981
    },
    {
      "rank": 89,
      "symbol": "usdtb",
      "price": 0.999429,
      "change24h": -0.0827
    },
    {
      "rank": 90,
      "symbol": "bonk",
      "price": 2.039e-05,
      "change24h": 2.15881
    },
    {
      "rank": 91,
      "symbol": "jup",
      "price": 0.502868,
      "change24h": 1.50019
    },
    {
      "rank": 92,
      "symbol": "lseth",
      "price": 4631.32,
      "change24h": 0.31409
    },
    {
      "rank": 93,
      "symbol": "lbtc",
      "price": 111161,
      "change24h": 0.73641
    },
    {
      "rank": 94,
      "symbol": "form",
      "price": 3.94,
      "change24h": 6.29944
    },
    {
      "rank": 95,
      "symbol": "qnt",
      "price": 102.97,
      "change24h": 0.7348
    },
    {
      "rank": 96,
      "symbol": "usdt",
      "price": 0.999845,
      "change24h": -0.017
    },
    {
      "rank": 97,
      "symbol": "ezeth",
      "price": 4535.77,
      "change24h": 0.43535
    },
    {
      "rank": 98,
      "symbol": "xdc",
      "price": 0.07885,
      "change24h": -0.13595
    },
    {
      "rank": 99,
      "symbol": "xaut",
      "price": 3606.62,
      "change24h": 0.0868
    },
    {
      "rank": 100,
      "symbol": "hash",
      "price": 0.02682394,
      "change24h": -6.61744
    },
    {
      "rank": 101,
      "symbol": "op",
      "price": 0.715406,
      "change24h": -0.28636
    },
    {
      "rank": 102,
      "symbol": "inj",
      "price": 13.02,
      "change24h": 0.31271
    },
    {
      "rank": 103,
      "symbol": "tia",
      "price": 1.64,
      "change24h": 1.84884
    },
    {
      "rank": 104,
      "symbol": "nexo",
      "price": 1.26,
      "change24h": -1.04052
    },
    {
      "rank": 105,
      "symbol": "meth",
      "price": 4601.24,
      "change24h": 0.49204
    },
    {
      "rank": 106,
      "symbol": "wbnb",
      "price": 873.33,
      "change24h": 1.45918
    },
    {
      "rank": 107,
      "symbol": "jupsol",
      "price": 231.68,
      "change24h": 1.15873
    },
    {
      "rank": 108,
      "symbol": "pyusd",
      "price": 0.999678,
      "change24h": 0.00574
    },
    {
      "rank": 109,
      "symbol": "solvbtc",
      "price": 111320,
      "change24h": 1.13224
    },
    {
      "rank": 110,
      "symbol": "stx",
      "price": 0.628904,
      "change24h": 1.62216
    },
    {
      "rank": 111,
      "symbol": "fdusd",
      "price": 0.997375,
      "change24h": -0.03258
    },
    {
      "rank": 112,
      "symbol": "spx",
      "price": 1.16,
      "change24h": 3.07533
    },
    {
      "rank": 113,
      "symbol": "syrupusdc",
      "price": 1.12,
      "change24h": -0.00482
    },
    {
      "rank": 114,
      "symbol": "crv",
      "price": 0.764551,
      "change24h": 0.65726
    },
    {
      "rank": 115,
      "symbol": "ldo",
      "price": 1.18,
      "change24h": 1.89635
    },
    {
      "rank": 116,
      "symbol": "usdc",
      "price": 0.999837,
      "change24h": 0.03984
    },
    {
      "rank": 117,
      "symbol": "paxg",
      "price": 3617.11,
      "change24h": -0.16649
    },
    {
      "rank": 118,
      "symbol": "aero",
      "price": 1.13,
      "change24h": -1.41696
    },
    {
      "rank": 119,
      "symbol": "imx",
      "price": 0.513791,
      "change24h": 0.14398
    },
    {
      "rank": 120,
      "symbol": "s",
      "price": 0.302956,
      "change24h": 1.1185
    },
    {
      "rank": 121,
      "symbol": "superoeth",
      "price": 4290.06,
      "change24h": 0.46719
    },
    {
      "rank": 122,
      "symbol": "saros",
      "price": 0.364865,
      "change24h": 1.39638
    },
    {
      "rank": 123,
      "symbol": "msol",
      "price": 269.72,
      "change24h": 1.12949
    },
    {
      "rank": 124,
      "symbol": "pyth",
      "price": 0.162744,
      "change24h": -0.83739
    },
    {
      "rank": 125,
      "symbol": "grt",
      "price": 0.088804,
      "change24h": 1.51388
    }
  ],
  "gainers": [
    {
      "symbol": "wld",
      "price": 1.044,
      "change24h": 14.36702
    },
    {
      "symbol": "wlfi",
      "price": 0.222232,
      "change24h": 12.63823
    },
    {
      "symbol": "m",
      "price": 1.89,
      "change24h": 8.96946
    },
    {
      "symbol": "form",
      "price": 3.94,
      "change24h": 6.29944
    },
    {
      "symbol": "pump",
      "price": 0.00482596,
      "change24h": 5.18698
    },
    {
      "symbol": "dot",
      "price": 3.98,
      "change24h": 4.68755
    },
    {
      "symbol": "fet",
      "price": 0.626133,
      "change24h": 4.21108
    },
    {
      "symbol": "flr",
      "price": 0.02173933,
      "change24h": 4.17981
    },
    {
      "symbol": "doge",
      "price": 0.222892,
      "change24h": 3.81451
    },
    {
      "symbol": "tao",
      "price": 327.17,
      "change24h": 3.64567
    },
    {
      "symbol": "sei",
      "price": 0.295103,
      "change24h": 3.36495
    },
    {
      "symbol": "kas",
      "price": 0.079895,
      "change24h": 3.13906
    },
    {
      "symbol": "spx",
      "price": 1.16,
      "change24h": 3.07533
    },
    {
      "symbol": "xrp",
      "price": 2.89,
      "change24h": 2.89365
    },
    {
      "symbol": "near",
      "price": 2.47,
      "change24h": 2.82811
    }
  ],
  "losers": [
    {
      "symbol": "hash",
      "price": 0.02682394,
      "change24h": -6.61744
    },
    {
      "symbol": "cro",
      "price": 0.259665,
      "change24h": -3.50608
    },
    {
      "symbol": "sky",
      "price": 0.07123,
      "change24h": -2.77757
    },
    {
      "symbol": "aero",
      "price": 1.13,
      "change24h": -1.41696
    },
    {
      "symbol": "nexo",
      "price": 1.26,
      "change24h": -1.04052
    },
    {
      "symbol": "pyth",
      "price": 0.162744,
      "change24h": -0.83739
    },
    {
      "symbol": "mnt",
      "price": 1.15,
      "change24h": -0.79829
    },
    {
      "symbol": "figr_heloc",
      "price": 1.0,
      "change24h": -0.46212
    },
    {
      "symbol": "aave",
      "price": 299.61,
      "change24h": -0.33236
    },
    {
      "symbol": "pol",
      "price": 0.275412,
      "change24h": -0.30274
    },
    {
      "symbol": "op",
      "price": 0.715406,
      "change24h": -0.28636
    },
    {
      "symbol": "paxg",
      "price": 3617.11,
      "change24h": -0.16649
    },
    {
      "symbol": "xdc",
      "price": 0.07885,
      "change24h": -0.13595
    },
    {
      "symbol": "leo",
      "price": 9.55,
      "change24h": -0.09069
    },
    {
      "symbol": "usdtb",
      "price": 0.999429,
      "change24h": -0.0827
    }
  ]
}