{
  "prices": [
    {
      "rank": 1,
      "symbol": "btc",
      "price": 95874,
      "change24h": -0.70223
    },
    {
      "rank": 2,
      "symbol": "eth",
      "price": 3195.94,
      "change24h": -0.43189
    },
    {
      "rank": 3,
      "symbol": "usdt",
      "price": 0.999525,
      "change24h": -0.00295
    },
    {
      "rank": 4,
      "symbol": "xrp",
      "price": 2.25,
      "change24h": -3.05421
    },
    {
      "rank": 5,
      "symbol": "bnb",
      "price": 936.97,
      "change24h": 1.07085
    },
    {
      "rank": 6,
      "symbol": "sol",
      "price": 143.16,
      "change24h": 0.50381
    },
    {
      "rank": 7,
      "symbol": "usdc",
      "price": 0.99975,
      "change24h": 0.00408
    },
    {
      "rank": 8,
      "symbol": "trx",
      "price": 0.292689,
      "change24h": -1.5509
    },
    {
      "rank": 9,
      "symbol": "steth",
      "price": 3200.28,
      "change24h": -0.31616
    },
    {
      "rank": 10,
      "symbol": "doge",
      "price": 0.163659,
      "change24h": 0.31899
    },
    {
      "rank": 11,
      "symbol": "ada",
      "price": 0.508341,
      "change24h": -1.33707
    },
    {
      "rank": 12,
      "symbol": "figr_heloc",
      "price": 1.035,
      "change24h": -0.42065
    },
    {
      "rank": 13,
      "symbol": "wsteth",
      "price": 3896.06,
      "change24h": -0.62902
    },
    {
      "rank": 14,
      "symbol": "wbtc",
      "price": 95985,
      "change24h": -0.50637
    },
    {
      "rank": 15,
      "symbol": "wbt",
      "price": 53.19,
      "change24h": 0.06718
    },
    {
      "rank": 16,
      "symbol": "wbeth",
      "price": 3461.56,
      "change24h": -0.29627
    },
    {
      "rank": 17,
      "symbol": "zec",
      "price": 645.05,
      "change24h": 13.87292
    },
    {
      "rank": 18,
      "symbol": "hype",
      "price": 38.76,
      "change24h": 3.76994
    },
    {
      "rank": 19,
      "symbol": "bch",
      "price": 505.36,
      "change24h": 1.79431
    },
    {
      "rank": 20,
      "symbol": "link",
      "price": 14.21,
      "change24h": -0.75869
    },
    {
      "rank": 21,
      "symbol": "usds",
      "price": 0.999823,
      "change24h": -0.0203
    },
    {
      "rank": 22,
      "symbol": "bsc-usd",
      "price": 0.999585,
      "change24h": 0.0652
    },
    {
      "rank": 23,
      "symbol": "xlm",
      "price": 0.260764,
      "change24h": -2.10212
    },
    {
      "rank": 24,
      "symbol": "weeth",
      "price": 3459.72,
      "change24h": -0.21892
    },
    {
      "rank": 25,
      "symbol": "leo",
      "price": 8.89,
      "change24h": -2.94933
    },
    {
      "rank": 26,
      "symbol": "weth",
      "price": 3200.66,
      "change24h": -0.35315
    },
    {
      "rank": 27,
      "symbol": "usde",
      "price": 0.998712,
      "change24h": 0.02515
    },
    {
      "rank": 28,
      "symbol": "xmr",
      "price": 430.82,
      "change24h": 8.7112
    },
    {
      "rank": 29,
      "symbol": "ltc",
      "price": 102.71,
      "change24h": 5.9909
    },
    {
      "rank": 30,
      "symbol": "cbbtc",
      "price": 95964,
      "change24h": -0.73734
    },
    {
      "rank": 31,
      "symbol": "avax",
      "price": 15.61,
      "change24h": 0.22747
    },
    {
      "rank": 32,
      "symbol": "hbar",
      "price": 0.156317,
      "change24h": -1.31955
    },
    {
      "rank": 33,
      "symbol": "sui",
      "price": 1.78,
      "change24h": -1.26142
    },
    {
      "rank": 34,
      "symbol": "shib",
      "price": 9.09e-06,
      "change24h": -1.74086
    },
    {
      "rank": 35,
      "symbol": "dot",
      "price": 2.87,
      "change24h": -0.2925
    },
    {
      "rank": 36,
      "symbol": "uni",
      "price": 7.45,
      "change24h": 3.15239
    },
    {
      "rank": 37,
      "symbol": "ton",
      "price": 1.85,
      "change24h": -0.53507
    },
    {
      "rank": 38,
      "symbol": "dai",
      "price": 0.999906,
      "change24h": 0.01386
    },
    {
      "rank": 39,
      "symbol": "susde",
      "price": 1.2,
      "change24h": 0.14504
    },
    {
      "rank": 40,
      "symbol": "cro",
      "price": 0.115426,
      "change24h": -1.28014
    },
    {
      "rank": 41,
      "symbol": "usdt0",
      "price": 0.999437,
      "change24h": -0.01277
    },
    {
      "rank": 42,
      "symbol": "cc",
      "price": 0.112644,
      "change24h": -5.73804
    },
    {
      "rank": 43,
      "symbol": "mnt",
      "price": 1.2,
      "change24h": -0.22156
    },
    {
      "rank": 44,
      "symbol": "wlfi",
      "price": 0.143227,
      "change24h": -4.16792
    },
    {
      "rank": 45,
      "symbol": "m",
      "price": 2.28,
      "change24h": -3.143
    },
    {
      "rank": 46,
      "symbol": "susds",
      "price": 1.077,
      "change24h": 0.20944
    },
    {
      "rank": 47,
      "symbol": "pyusd",
      "price": 1.0,
      "change24h": 0.01004
    },
    {
      "rank": 48,
      "symbol": "tao",
      "price": 337.5,
      "change24h": 0.22623
    },
    {
      "rank": 49,
      "symbol": "near",
      "price": 2.45,
      "change24h": 1.59984
    },
    {
      "rank": 50,
      "symbol": "icp",
      "price": 5.23,
      "change24h": -5.86607
    },
    {
      "rank": 51,
      "symbol": "usd1",
      "price": 0.998956,
      "change24h": 0.07726
    },
    {
      "rank": 52,
      "symbol": "aave",
      "price": 180.8,
      "change24h": -0.07091
    },
    {
      "rank": 53,
      "symbol": "bgb",
      "price": 3.87,
      "change24h": 0.63107
    },
    {
      "rank": 54,
      "symbol": "c1usd",
      "price": 0.993179,
      "change24h": -0.68978
    },
    {
      "rank": 55,
      "symbol": "buidl",
      "price": 1.0,
      "change24h": 0.0
    },
    {
      "rank": 56,
      "symbol": "etc",
      "price": 15.35,
      "change24h": 2.76843
    },
    {
      "rank": 57,
      "symbol": "okb",
      "price": 112.64,
      "change24h": -0.05968
    },
    {
      "rank": 58,
      "symbol": "aster",
      "price": 1.13,
      "change24h": 2.7948
    },
    {
      "rank": 59,
      "symbol": "apt",
      "price": 2.94,
      "change24h": -4.76759
    },
    {
      "rank": 60,
      "symbol": "pepe",
      "price": 5.07e-06,
      "change24h": -1.68504
    },
    {
      "rank": 61,
      "symbol": "xaut",
      "price": 4068.02,
      "change24h": -0.14148
    },
    {
      "rank": 62,
      "symbol": "pump",
      "price": 0.00358999,
      "change24h": -0.04392
    },
    {
      "rank": 63,
      "symbol": "usdf",
      "price": 0.999049,
      "change24h": 0.06916
    },
    {
      "rank": 64,
      "symbol": "ena",
      "price": 0.281043,
      "change24h": -1.58196
    },
    {
      "rank": 65,
      "symbol": "jitosol",
      "price": 177.61,
      "change24h": 0.40993
    },
    {
      "rank": 66,
      "symbol": "jlp",
      "price": 4.79,
      "change24h": 0.15463
    },
    {
      "rank": 67,
      "symbol": "weth",
      "price": 3200.33,
      "change24h": -0.30807
    },
    {
      "rank": 68,
      "symbol": "sol",
      "price": 142.9,
      "change24h": 0.4554
    },
    {
      "rank": 69,
      "symbol": "ondo",
      "price": 0.585938,
      "change24h": -1.89367
    },
    {
      "rank": 70,
      "symbol": "pi",
      "price": 0.218585,
      "change24h": 0.89851
    },
    {
      "rank": 71,
      "symbol": "htx",
      "price": 1.8e-06,
      "change24h": -0.77006
    },
    {
      "rank": 72,
      "symbol": "pol",
      "price": 0.156205,
      "change24h": -1.84869
    },
    {
      "rank": 73,
      "symbol": "wld",
      "price": 0.701166,
      "change24h": -3.35668
    },
    {
      "rank": 74,
      "symbol": "kcs",
      "price": 12.29,
      "change24h": -0.57298
    },
    {
      "rank": 75,
      "symbol": "hash",
      "price": 0.03080304,
      "change24h": 13.60868
    },
    {
      "rank": 76,
      "symbol": "usdtb",
      "price": 0.998788,
      "change24h": -0.05865
    },
    {
      "rank": 77,
      "symbol": "fil",
      "price": 2.1,
      "change24h": 5.15427
    },
    {
      "rank": 78,
      "symbol": "algo",
      "price": 0.165187,
      "change24h": 0.46308
    },
    {
      "rank": 79,
      "symbol": "trump",
      "price": 7.21,
      "change24h": -1.0771
    },
    {
      "rank": 80,
      "symbol": "reth",
      "price": 3673.85,
      "change24h": -0.36528
    },
    {
      "rank": 81,
      "symbol": "atom",
      "price": 2.88,
      "change24h": 0.11757
    },
    {
      "rank": 82,
      "symbol": "vet",
      "price": 0.01586085,
      "change24h": -0.30214
    },
    {
      "rank": 83,
      "symbol": "paxg",
      "price": 4091.19,
      "change24h": 0.16552
    },
    {
      "rank": 84,
      "symbol": "arb",
      "price": 0.24351,
      "change24h": -0.97455
    },
    {
      "rank": 85,
      "symbol": "syrupusdt",
      "price": 1.1,
      "change24h": -0.09561
    },
    {
      "rank": 86,
      "symbol": "bfusd",
      "price": 0.999297,
      "change24h": -0.00174
    },
    {
      "rank": 87,
      "symbol": "bnsol",
      "price": 154.72,
      "change24h": 0.43954
    },
    {
      "rank": 88,
      "symbol": "usdc",
      "price": 0.999946,
      "change24h": 0.01927
    },
    {
      "rank": 89,
      "symbol": "khype",
      "price": 38.9,
      "change24h": 3.95841
    },
    {
      "rank": 90,
      "symbol": "gt",
      "price": 10.91,
      "change24h": -1.09596
    },
    {
      "rank": 91,
      "symbol": "wbnb",
      "price": 937.28,
      "change24h": 1.12209
    },
    {
      "rank": 92,
      "symbol": "kas",
      "price": 0.04533125,
      "change24h": -2.62202
    },
    {
      "rank": 93,
      "symbol": "syrupusdc",
      "price": 1.14,
      "change24h": 0.00469
    },
    {
      "rank": 94,
      "symbol": "qnt",
      "price": 82.55,
      "change24h": -4.41598
    },
    {
      "rank": 95,
      "symbol": "sky",
      "price": 0.052117,
      "change24h": -1.54831
    },
    {
      "rank": 96,
      "symbol": "fbtc",
      "price": 96274,
      "change24h": -0.22016
    },
    {
      "rank": 97,
      "symbol": "rseth",
      "price": 3381.06,
      "change24h": -0.51959
    },
    {
      "rank": 98,
      "symbol": "render",
      "price": 2.17,
      "change24h": -1.0134
    },
    {
      "rank": 99,
      "symbol": "usdg",
      "price": 0.999623,
      "change24h": -0.01064
    },
    {
      "rank": 100,
      "symbol": "flr",
      "price": 0.01411559,
      "change24h": -1.22072
    },
    {
      "rank": 101,
      "symbol": "lbtc",
      "price": 95929,
      "change24h": -0.76762
    },
    {
      "rank": 102,
      "symbol": "rlusd",
      "price": 1.0,
      "change24h": -0.05303
    },
    {
      "rank": 103,
      "symbol": "lseth",
      "price": 3446.48,
      "change24h": -1.08754
    },
    {
      "rank": 104,
      "symbol": "usyc",
      "price": 1.11,
      "change24h": 0.0
    },
    {
      "rank": 105,
      "symbol": "ip",
      "price": 3.24,
      "change24h": 1.24718
    },
    {
      "rank": 106,
      "symbol": "morpho",
      "price": 2.0,
      "change24h": -3.08697
    },
    {
      "rank": 107,
      "symbol": "sei",
      "price": 0.165078,
      "change24h": 0.22373
    },
    {
      "rank": 108,
      "symbol": "nexo",
      "price": 1.012,
      "change24h": -0.96767
    },
    {
      "rank": 109,
      "symbol": "dash",
      "price": 80.88,
      "change24h": 12.343
    },
    {
      "rank": 110,
      "symbol": "solvbtc",
      "price": 95847,
      "change24h": -0.62043
    },
    {
      "rank": 111,
      "symbol": "xdc",
      "price": 0.054762,
      "change24h": 3.23322
    },
    {
      "rank": 112,
      "symbol": "ezeth",
      "price": 3406.62,
      "change24h": -0.46977
    },
    {
      "rank": 113,
      "symbol": "fdusd",
      "price": 0.996692,
      "change24h": -0.11219
    },
    {
      "rank": 114,
      "symbol": "jup",
      "price": 0.288647,
      "change24h": -2.05189
    },
    {
      "rank": 115,
      "symbol": "bonk",
      "price": 1.117e-05,
      "change24h": -1.96526
    },
    {
      "rank": 116,
      "symbol": "strk",
      "price": 0.197036,
      "change24h": 12.77656
    },
    {
      "rank": 117,
      "symbol": "pengu",
      "price": 0.01324045,
      "change24h": -0.35136
    },
    {
      "rank": 118,
      "symbol": "ustb",
      "price": 10.89,
      "change24h": 0.0
    },
    {
      "rank": 119,
      "symbol": "cake",
      "price": 2.41,
      "change24h": -0.34231
    },
    {
      "rank": 120,
      "symbol": "meth",
      "price": 3457.39,
      "change24h": -0.41329
    },
    {
      "rank": 121,
      "symbol": "rain",
      "price": 0.00333813,
      "change24h": -0.54577
    },
    {
      "rank": 122,
      "symbol": "aero",
      "price": 0.868771,
      "change24h": 0.41396
    },
    {
      "rank": 123,
      "symbol": "ousg",
      "price": 113.3,
      "change24h": 0.02016
    },
    {
      "rank": 124,
      "symbol": "wbtc",
      "price": 95952,
      "change24h": -0.61781
    },
    {
      "rank": 125,
      "symbol": "ftn",
      "price": 1.78,
      "change24h": 2.06672
    }
  ],
  "gainers": [
    {
      "symbol": "zec",
      "price": 645.05,
      "change24h": 13.87292
    },
    {
      "symbol": "hash",
      "price": 0.03080304,
      "change24h": 13.60868
    },
    {
      "symbol": "strk",
      "price": 0.197036,
      "change24h": 12.77656
    },
    {
      "symbol": "dash",
      "price": 80.88,
      "change24h": 12.343
    },
    {
      "symbol": "xmr",
      "price": 430.82,
      "change24h": 8.7112
    },
    {
      "symbol": "ltc",
      "price": 102.71,
      "change24h": 5.9909
    },
    {
      "symbol": "fil",
      "price": 2.1,
      "change24h": 5.15427
    },
    {
      "symbol": "khype",
      "price": 38.9,
      "change24h": 3.95841
    },
    {
      "symbol": "hype",
      "price": 38.76,
      "change24h": 3.76994
    },
    {
      "symbol": "xdc",
      "price": 0.054762,
      "change24h": 3.23322
    },
    {
      "symbol": "uni",
      "price": 7.45,
      "change24h": 3.15239
    },
    {
      "symbol": "aster",
      "price": 1.13,
      "change24h": 2.7948
    },
    {
      "symbol": "etc",
      "price": 15.35,
      "change24h": 2.76843
    },
    {
      "symbol": "ftn",
      "price": 1.78,
      "change24h": 2.06672
    },
    {
      "symbol": "bch",
      "price": 505.36,
      "change24h": 1.79431
    }
  ],
  "losers": [
    {
      "symbol": "icp",
      "price": 5.23,
      "change24h": -5.86607
    },
    {
      "symbol": "cc",
      "price": 0.112644,
      "change24h": -5.73804
    },
    {
      "symbol": "apt",
      "price": 2.94,
      "change24h": -4.76759
    },
    {
      "symbol": "qnt",
      "price": 82.55,
      "change24h": -4.41598
    },
    {
      "symbol": "wlfi",
      "price": 0.143227,
      "change24h": -4.16792
    },
    {
      "symbol": "wld",
      "price": 0.701166,
      "change24h": -3.35668
    },
    {
      "symbol": "m",
      "price": 2.28,
      "change24h": -3.143
    },
    {
      "symbol": "morpho",
      "price": 2.0,
      "change24h": -3.08697
    },
    {
      "symbol": "xrp",
      "price": 2.25,
      "change24h": -3.05421
    },
    {
      "symbol": "leo",
      "price": 8.89,
      "change24h": -2.94933
    },
    {
      "symbol": "kas",
      "price": 0.04533125,
      "change24h": -2.62202
    },
    {
      "symbol": "xlm",
      "price": 0.260764,
      "change24h": -2.10212
    },
    {
      "symbol": "jup",
      "price": 0.288647,
      "change24h": -2.05189
    },
    {
      "symbol": "bonk",
      "price": 1.117e-05,
      "change24h": -1.96526
    },
    {
      "symbol": "ondo",
      "price": 0.585938,
      "change24h": -1.89367
    }
  ]
}