{
  "prices": [
    {
      "rank": 1,
      "symbol": "btc",
      "price": 86777,
      "change24h": 2.66159
    },
    {
      "rank": 2,
      "symbol": "eth",
      "price": 2833.4,
      "change24h": 3.32086
    },
    {
      "rank": 3,
      "symbol": "usdt",
      "price": 0.99968,
      "change24h": 0.01412
    },
    {
      "rank": 4,
      "symbol": "xrp",
      "price": 2.05,
      "change24h": 7.03903
    },
    {
      "rank": 5,
      "symbol": "bnb",
      "price": 848.52,
      "change24h": 2.87631
    },
    {
      "rank": 6,
      "symbol": "usdc",
      "price": 0.999694,
      "change24h": -0.00064
    },
    {
      "rank": 7,
      "symbol": "sol",
      "price": 131.71,
      "change24h": 4.11627
    },
    {
      "rank": 8,
      "symbol": "trx",
      "price": 0.274918,
      "change24h": 0.11716
    },
    {
      "rank": 9,
      "symbol": "steth",
      "price": 2831.37,
      "change24h": 3.47292
    },
    {
      "rank": 10,
      "symbol": "doge",
      "price": 0.145104,
      "change24h": 5.23205
    },
    {
      "rank": 11,
      "symbol": "ada",
      "price": 0.413074,
      "change24h": 4.23898
    },
    {
      "rank": 12,
      "symbol": "figr_heloc",
      "price": 1.026,
      "change24h": -0.27307
    },
    {
      "rank": 13,
      "symbol": "wbt",
      "price": 57.24,
      "change24h": 1.65178
    },
    {
      "rank": 14,
      "symbol": "wsteth",
      "price": 3453.8,
      "change24h": 3.5476
    },
    {
      "rank": 15,
      "symbol": "bch",
      "price": 549.07,
      "change24h": 0.54803
    },
    {
      "rank": 16,
      "symbol": "wbtc",
      "price": 86609,
      "change24h": 3.06232
    },
    {
      "rank": 17,
      "symbol": "wbeth",
      "price": 3069.33,
      "change24h": 3.94286
    },
    {
      "rank": 18,
      "symbol": "zec",
      "price": 573.76,
      "change24h": 11.87481
    },
    {
      "rank": 19,
      "symbol": "usds",
      "price": 0.99968,
      "change24h": -0.00555
    },
    {
      "rank": 20,
      "symbol": "bsc-usd",
      "price": 0.999571,
      "change24h": 0.04058
    },
    {
      "rank": 21,
      "symbol": "link",
      "price": 12.59,
      "change24h": 5.71354
    },
    {
      "rank": 22,
      "symbol": "leo",
      "price": 9.5,
      "change24h": 1.50468
    },
    {
      "rank": 23,
      "symbol": "hype",
      "price": 31.13,
      "change24h": -4.22864
    },
    {
      "rank": 24,
      "symbol": "xlm",
      "price": 0.241801,
      "change24h": 5.76848
    },
    {
      "rank": 25,
      "symbol": "weth",
      "price": 2833.37,
      "change24h": 3.30229
    },
    {
      "rank": 26,
      "symbol": "usde",
      "price": 0.998725,
      "change24h": 0.02971
    },
    {
      "rank": 27,
      "symbol": "xmr",
      "price": 395.57,
      "change24h": 10.07099
    },
    {
      "rank": 28,
      "symbol": "weeth",
      "price": 3066.94,
      "change24h": 3.53878
    },
    {
      "rank": 29,
      "symbol": "cbbtc",
      "price": 86890,
      "change24h": 3.09081
    },
    {
      "rank": 30,
      "symbol": "ltc",
      "price": 83.54,
      "change24h": 2.12517
    },
    {
      "rank": 31,
      "symbol": "hbar",
      "price": 0.142447,
      "change24h": 10.68101
    },
    {
      "rank": 32,
      "symbol": "avax",
      "price": 13.35,
      "change24h": 1.25037
    },
    {
      "rank": 33,
      "symbol": "sui",
      "price": 1.37,
      "change24h": 2.41347
    },
    {
      "rank": 34,
      "symbol": "shib",
      "price": 7.97e-06,
      "change24h": 4.05808
    },
    {
      "rank": 35,
      "symbol": "dai",
      "price": 1.0,
      "change24h": 0.0683
    },
    {
      "rank": 36,
      "symbol": "susde",
      "price": 1.2,
      "change24h": -0.02772
    },
    {
      "rank": 37,
      "symbol": "wlfi",
      "price": 0.149776,
      "change24h": 3.90546
    },
    {
      "rank": 38,
      "symbol": "cro",
      "price": 0.107881,
      "change24h": 9.09576
    },
    {
      "rank": 39,
      "symbol": "usdt0",
      "price": 0.999642,
      "change24h": 0.03618
    },
    {
      "rank": 40,
      "symbol": "uni",
      "price": 6.23,
      "change24h": 1.96678
    },
    {
      "rank": 41,
      "symbol": "dot",
      "price": 2.34,
      "change24h": 2.19571
    },
    {
      "rank": 42,
      "symbol": "susds",
      "price": 1.077,
      "change24h": 0.25084
    },
    {
      "rank": 43,
      "symbol": "ton",
      "price": 1.51,
      "change24h": -0.23514
    },
    {
      "rank": 44,
      "symbol": "pyusd",
      "price": 0.999711,
      "change24h": 0.01022
    },
    {
      "rank": 45,
      "symbol": "mnt",
      "price": 1.018,
      "change24h": 6.02721
    },
    {
      "rank": 46,
      "symbol": "m",
      "price": 1.98,
      "change24h": 1.16812
    },
    {
      "rank": 47,
      "symbol": "tao",
      "price": 287.74,
      "change24h": 6.97097
    },
    {
      "rank": 48,
      "symbol": "cc",
      "price": 0.076672,
      "change24h": 0.10025
    },
    {
      "rank": 49,
      "symbol": "usd1",
      "price": 0.998934,
      "change24h": -0.01072
    },
    {
      "rank": 50,
      "symbol": "c1usd",
      "price": 1.006,
      "change24h": 0.20961
    },
    {
      "rank": 51,
      "symbol": "aave",
      "price": 163.71,
      "change24h": 3.95617
    },
    {
      "rank": 52,
      "symbol": "bgb",
      "price": 3.54,
      "change24h": -0.31864
    },
    {
      "rank": 53,
      "symbol": "near",
      "price": 1.86,
      "change24h": 1.53691
    },
    {
      "rank": 54,
      "symbol": "buidl",
      "price": 1.0,
      "change24h": 0.0
    },
    {
      "rank": 55,
      "symbol": "aster",
      "price": 1.11,
      "change24h": -4.27929
    },
    {
      "rank": 56,
      "symbol": "icp",
      "price": 4.09,
      "change24h": -1.13545
    },
    {
      "rank": 57,
      "symbol": "okb",
      "price": 105.07,
      "change24h": 6.94881
    },
    {
      "rank": 58,
      "symbol": "usdf",
      "price": 0.998889,
      "change24h": 0.28223
    },
    {
      "rank": 59,
      "symbol": "etc",
      "price": 13.67,
      "change24h": 1.81935
    },
    {
      "rank": 60,
      "symbol": "xaut",
      "price": 4033.76,
      "change24h": -0.53277
    },
    {
      "rank": 61,
      "symbol": "pi",
      "price": 0.240101,
      "change24h": -0.00848
    },
    {
      "rank": 62,
      "symbol": "jitosol",
      "price": 163.88,
      "change24h": 4.5059
    },
    {
      "rank": 63,
      "symbol": "jlp",
      "price": 4.56,
      "change24h": 2.5922
    },
    {
      "rank": 64,
      "symbol": "ena",
      "price": 0.238163,
      "change24h": 3.32045
    },
    {
      "rank": 65,
      "symbol": "pepe",
      "price": 4.18e-06,
      "change24h": 2.98825
    },
    {
      "rank": 66,
      "symbol": "apt",
      "price": 2.35,
      "change24h": 1.3376
    },
    {
      "rank": 67,
      "symbol": "weth",
      "price": 2834.04,
      "change24h": 2.9333
    },
    {
      "rank": 68,
      "symbol": "sol",
      "price": 131.6,
      "change24h": 4.01909
    },
    {
      "rank": 69,
      "symbol": "htx",
      "price": 1.7e-06,
      "change24h": -0.35189
    },
    {
      "rank": 70,
      "symbol": "pump",
      "price": 0.00260759,
      "change24h": -1.59417
    },
    {
      "rank": 71,
      "symbol": "kcs",
      "price": 11.59,
      "change24h": 3.06987
    },
    {
      "rank": 72,
      "symbol": "ondo",
      "price": 0.473903,
      "change24h": 2.81846
    },
    {
      "rank": 73,
      "symbol": "wld",
      "price": 0.610985,
      "change24h": 1.96154
    },
    {
      "rank": 74,
      "symbol": "pol",
      "price": 0.135387,
      "change24h": 2.44985
    },
    {
      "rank": 75,
      "symbol": "hash",
      "price": 0.02634451,
      "change24h": 18.33135
    },
    {
      "rank": 76,
      "symbol": "paxg",
      "price": 4049.01,
      "change24h": -0.22107
    },
    {
      "rank": 77,
      "symbol": "usdtb",
      "price": 1.0,
      "change24h": 0.10418
    },
    {
      "rank": 78,
      "symbol": "bfusd",
      "price": 0.999513,
      "change24h": 0.01179
    },
    {
      "rank": 79,
      "symbol": "syrupusdc",
      "price": 1.14,
      "change24h": 0.02777
    },
    {
      "rank": 80,
      "symbol": "usdc",
      "price": 0.999411,
      "change24h": -0.0355
    },
    {
      "rank": 81,
      "symbol": "trump",
      "price": 6.37,
      "change24h": 1.55451
    },
    {
      "rank": 82,
      "symbol": "algo",
      "price": 0.139882,
      "change24h": 3.99294
    },
    {
      "rank": 83,
      "symbol": "reth",
      "price": 3249.94,
      "change24h": 3.78965
    },
    {
      "rank": 84,
      "symbol": "atom",
      "price": 2.52,
      "change24h": 1.95853
    },
    {
      "rank": 85,
      "symbol": "fil",
      "price": 1.64,
      "change24h": 1.65451
    },
    {
      "rank": 86,
      "symbol": "gt",
      "price": 10.05,
      "change24h": 3.69586
    },
    {
      "rank": 87,
      "symbol": "usyc",
      "price": 1.11,
      "change24h": -0.00917
    },
    {
      "rank": 88,
      "symbol": "wbnb",
      "price": 847.85,
      "change24h": 2.54043
    },
    {
      "rank": 89,
      "symbol": "rlusd",
      "price": 0.999718,
      "change24h": 0.01252
    },
    {
      "rank": 90,
      "symbol": "usdg",
      "price": 0.999673,
      "change24h": 7e-05
    },
    {
      "rank": 91,
      "symbol": "bnsol",
      "price": 142.52,
      "change24h": 3.85417
    },
    {
      "rank": 92,
      "symbol": "arb",
      "price": 0.202331,
      "change24h": 1.95444
    },
    {
      "rank": 93,
      "symbol": "qnt",
      "price": 77.23,
      "change24h": 5.97948
    },
    {
      "rank": 94,
      "symbol": "vet",
      "price": 0.01301127,
      "change24h": 2.47845
    },
    {
      "rank": 95,
      "symbol": "kas",
      "price": 0.03977767,
      "change24h": 5.59939
    },
    {
      "rank": 96,
      "symbol": "flr",
      "price": 0.01327384,
      "change24h": 7.91342
    },
    {
      "rank": 97,
      "symbol": "fbtc",
      "price": 86457,
      "change24h": 2.71072
    },
    {
      "rank": 98,
      "symbol": "rseth",
      "price": 2996.38,
      "change24h": 3.69665
    },
    {
      "rank": 99,
      "symbol": "lbtc",
      "price": 86885,
      "change24h": 3.2254
    },
    {
      "rank": 100,
      "symbol": "khype",
      "price": 31.31,
      "change24h": -3.97886
    },
    {
      "rank": 101,
      "symbol": "sky",
      "price": 0.04266523,
      "change24h": 2.82006
    },
    {
      "rank": 102,
      "symbol": "xdc",
      "price": 0.051993,
      "change24h": 2.8094
    },
    {
      "rank": 103,
      "symbol": "ustb",
      "price": 10.9,
      "change24h": 0.0
    },
    {
      "rank": 104,
      "symbol": "lseth",
      "price": 3028.91,
      "change24h": 3.91965
    },
    {
      "rank": 105,
      "symbol": "nexo",
      "price": 0.939432,
      "change24h": 3.52989
    },
    {
      "rank": 106,
      "symbol": "fdusd",
      "price": 0.99772,
      "change24h": 0.08587
    },
    {
      "rank": 107,
      "symbol": "solvbtc",
      "price": 86392,
      "change24h": 2.86801
    },
    {
      "rank": 108,
      "symbol": "render",
      "price": 1.73,
      "change24h": 3.49842
    },
    {
      "rank": 109,
      "symbol": "sei",
      "price": 0.132507,
      "change24h": 1.55391
    },
    {
      "rank": 110,
      "symbol": "morpho",
      "price": 1.5,
      "change24h": 0.65191
    },
    {
      "rank": 111,
      "symbol": "ezeth",
      "price": 3015.25,
      "change24h": 3.43632
    },
    {
      "rank": 112,
      "symbol": "ousg",
      "price": 113.38,
      "change24h": 0.0
    },
    {
      "rank": 113,
      "symbol": "cake",
      "price": 2.27,
      "change24h": 4.13329
    },
    {
      "rank": 114,
      "symbol": "jup",
      "price": 0.23591,
      "change24h": -0.27204
    },
    {
      "rank": 115,
      "symbol": "jaaa",
      "price": 1.014,
      "change24h": 0.0
    },
    {
      "rank": 116,
      "symbol": "fet",
      "price": 0.290755,
      "change24h": 6.8965
    },
    {
      "rank": 117,
      "symbol": "dash",
      "price": 60.32,
      "change24h": 8.82485
    },
    {
      "rank": 118,
      "symbol": "ftn",
      "price": 1.74,
      "change24h": 1.34057
    },
    {
      "rank": 119,
      "symbol": "ip",
      "price": 2.26,
      "change24h": -0.04998
    },
    {
      "rank": 120,
      "symbol": "bonk",
      "price": 8.94e-06,
      "change24h": 3.3278
    },
    {
      "rank": 121,
      "symbol": "syrupusdt",
      "price": 1.1,
      "change24h": 0.03199
    },
    {
      "rank": 122,
      "symbol": "meth",
      "price": 3057.3,
      "change24h": 3.26645
    },
    {
      "rank": 123,
      "symbol": "wbtc",
      "price": 86649,
      "change24h": 2.88368
    },
    {
      "rank": 124,
      "symbol": "strk",
      "price": 0.149903,
      "change24h": -12.27975
    },
    {
      "rank": 125,
      "symbol": "usdy",
      "price": 1.089,
      "change24h": -2.74878
    }
  ],
  "gainers": [
    {
      "symbol": "hash",
      "price": 0.02634451,
      "change24h": 18.33135
    },
    {
      "symbol": "zec",
      "price": 573.76,
      "change24h": 11.87481
    },
    {
      "symbol": "hbar",
      "price": 0.142447,
      "change24h": 10.68101
    },
    {
      "symbol": "xmr",
      "price": 395.57,
      "change24h": 10.07099
    },
    {
      "symbol": "cro",
      "price": 0.107881,
      "change24h": 9.09576
    },
    {
      "symbol": "dash",
      "price": 60.32,
      "change24h": 8.82485
    },
    {
      "symbol": "flr",
      "price": 0.01327384,
      "change24h": 7.91342
    },
    {
      "symbol": "xrp",
      "price": 2.05,
      "change24h": 7.03903
    },
    {
      "symbol": "tao",
      "price": 287.74,
      "change24h": 6.97097
    },
    {
      "symbol": "okb",
      "price": 105.07,
      "change24h": 6.94881
    },
    {
      "symbol": "fet",
      "price": 0.290755,
      "change24h": 6.8965
    },
    {
      "symbol": "mnt",
      "price": 1.018,
      "change24h": 6.02721
    },
    {
      "symbol": "qnt",
      "price": 77.23,
      "change24h": 5.97948
    },
    {
      "symbol": "xlm",
      "price": 0.241801,
      "change24h": 5.76848
    },
    {
      "symbol": "link",
      "price": 12.59,
      "change24h": 5.71354
    }
  ],
  "losers": [
    {
      "symbol": "strk",
      "price": 0.149903,
      "change24h": -12.27975
    },
    {
      "symbol": "aster",
      "price": 1.11,
      "change24h": -4.27929
    },
    {
      "symbol": "hype",
      "price": 31.13,
      "change24h": -4.22864
    },
    {
      "symbol": "khype",
      "price": 31.31,
      "change24h": -3.97886
    },
    {
      "symbol": "usdy",
      "price": 1.089,
      "change24h": -2.74878
    },
    {
      "symbol": "pump",
      "price": 0.00260759,
      "change24h": -1.59417
    },
    {
      "symbol": "icp",
      "price": 4.09,
      "change24h": -1.13545
    },
    {
      "symbol": "xaut",
      "price": 4033.76,
      "change24h": -0.53277
    },
    {
      "symbol": "htx",
      "price": 1.7e-06,
      "change24h": -0.35189
    },
    {
      "symbol": "bgb",
      "price": 3.54,
      "change24h": -0.31864
    },
    {
      "symbol": "figr_heloc",
      "price": 1.026,
      "change24h": -0.27307
    },
    {
      "symbol": "jup",
      "price": 0.23591,
      "change24h": -0.27204
    },
    {
      "symbol": "ton",
      "price": 1.51,
      "change24h": -0.23514
    },
    {
      "symbol": "paxg",
      "price": 4049.01,
      "change24h": -0.22107
    },
    {
      "symbol": "ip",
      "price": 2.26,
      "change24h": -0.04998
    }
  ]
}